[{"DayOfWeek": 2, "Month": 5, "Hour": 12, "District": 352, "Price": 732.0, "Duration": 38, "Length": 39.0}, {"DayOfWeek": 2, "Month": 5, "Hour": 12, "District": 356, "Price": 340.0, "Duration": 17, "Length": 5.1}, {"DayOfWeek": 2, "Month": 5, "Hour": 12, "District": 90, "Price": 1325.0, "Duration": 33, "Length": 27.3}, {"DayOfWeek": 2, "Month": 5, "Hour": 12, "District": 270, "Price": 349.0, "Duration": 34, "Length": 30.0}, {"DayOfWeek": 2, "Month": 5, "Hour": 12, "District": 897, "Price": 617.0, "Duration": 20, "Length": 7.0}, {"DayOfWeek": 2, "Month": 5, "Hour": 12, "District": 834, "Price": 578.0, "Duration": 24, "Length": 8.8}, {"DayOfWeek": 2, "Month": 5, "Hour": 12, "District": 735, "Price": 463.0, "Duration": 20, "Length": 7.1}, {"DayOfWeek": 2, "Month": 5, "Hour": 12, "District": 22, "Price": 483.0, "Duration": 19, "Length": 7.7}, {"DayOfWeek": 2, "Month": 5, "Hour": 12, "District": 733, "Price": 644.0, "Duration": 22, "Length": 8.6}, {"DayOfWeek": 2, "Month": 5, "Hour": 12, "District": 503, "Price": 857.0, "Duration": 29, "Length": 16.9}, {"DayOfWeek": 2, "Month": 5, "Hour": 12, "District": 979, "Price": 527.0, "Duration": 11, "Length": 5.8}, {"DayOfWeek": 2, "Month": 5, "Hour": 12, "District": 732, "Price": 569.0, "Duration": 17, "Length": 10.2}, {"DayOfWeek": 2, "Month": 5, "Hour": 12, "District": 94, "Price": 478.0, "Duration": 22, "Length": 10.3}, {"DayOfWeek": 2, "Month": 5, "Hour": 12, "District": 271, "Price": 598.0, "Duration": 16, "Length": 7.4}, {"DayOfWeek": 2, "Month": 5, "Hour": 12, "District": 145, "Price": 958.0, "Duration": 36, "Length": 17.8}, {"DayOfWeek": 2, "Month": 5, "Hour": 12, "District": 427, "Price": 369.0, "Duration": 44, "Length": 24.2}, {"DayOfWeek": 2, "Month": 5, "Hour": 12, "District": 164, "Price": 606.0, "Duration": 21, "Length": 11.9}, {"DayOfWeek": 2, "Month": 5, "Hour": 12, "District": 427, "Price": 629.0, "Duration": 23, "Length": 13.3}, {"DayOfWeek": 2, "Month": 5, "Hour": 12, "District": 417, "Price": 604.0, "Duration": 18, "Length": 4.3}, {"DayOfWeek": 2, "Month": 5, "Hour": 12, "District": 362, "Price": 300.0, "Duration": 7, "Length": 2.0}, {"DayOfWeek": 2, "Month": 5, "Hour": 12, "District": 385, "Price": 279.0, "Duration": 35, "Length": 20.7}, {"DayOfWeek": 2, "Month": 5, "Hour": 12, "District": 195, "Price": 279.0, "Duration": 40, "Length": 28.3}, {"DayOfWeek": 2, "Month": 5, "Hour": 12, "District": 419, "Price": 800.0, "Duration": 27, "Length": 13.4}, {"DayOfWeek": 2, "Month": 5, "Hour": 12, "District": 541, "Price": 723.0, "Duration": 22, "Length": 22.1}, {"DayOfWeek": 2, "Month": 5, "Hour": 12, "District": 622, "Price": 542.0, "Duration": 25, "Length": 6.1}, {"DayOfWeek": 2, "Month": 5, "Hour": 12, "District": 693, "Price": 834.0, "Duration": 33, "Length": 20.6}, {"DayOfWeek": 2, "Month": 5, "Hour": 12, "District": 40, "Price": 534.0, "Duration": 18, "Length": 5.4}, {"DayOfWeek": 2, "Month": 5, "Hour": 12, "District": 565, "Price": 345.0, "Duration": 9, "Length": 3.6}, {"DayOfWeek": 2, "Month": 5, "Hour": 12, "District": 29, "Price": 509.0, "Duration": 23, "Length": 18.1}, {"DayOfWeek": 2, "Month": 5, "Hour": 12, "District": 234, "Price": 229.0, "Duration": 43, "Length": 24.1}, {"DayOfWeek": 2, "Month": 5, "Hour": 12, "District": 313, "Price": 299.0, "Duration": 36, "Length": 19.7}, {"DayOfWeek": 2, "Month": 5, "Hour": 12, "District": 707, "Price": 716.0, "Duration": 27, "Length": 11.9}, {"DayOfWeek": 2, "Month": 5, "Hour": 12, "District": 220, "Price": 778.0, "Duration": 27, "Length": 10.6}, {"DayOfWeek": 2, "Month": 5, "Hour": 12, "District": 449, "Price": 612.0, "Duration": 19, "Length": 6.7}, {"DayOfWeek": 2, "Month": 5, "Hour": 12, "District": 457, "Price": 503.0, "Duration": 12, "Length": 4.9}, {"DayOfWeek": 2, "Month": 5, "Hour": 12, "District": 634, "Price": 466.0, "Duration": 13, "Length": 5.9}, {"DayOfWeek": 2, "Month": 5, "Hour": 12, "District": 186, "Price": 814.0, "Duration": 25, "Length": 10.0}, {"DayOfWeek": 2, "Month": 5, "Hour": 12, "District": 115, "Price": 1030.0, "Duration": 36, "Length": 14.0}, {"DayOfWeek": 2, "Month": 5, "Hour": 12, "District": 174, "Price": 773.0, "Duration": 27, "Length": 16.4}, {"DayOfWeek": 2, "Month": 5, "Hour": 12, "District": 618, "Price": 321.0, "Duration": 8, "Length": 3.4}, {"DayOfWeek": 2, "Month": 5, "Hour": 12, "District": 145, "Price": 819.0, "Duration": 31, "Length": 13.3}, {"DayOfWeek": 2, "Month": 5, "Hour": 12, "District": 33, "Price": 465.0, "Duration": 23, "Length": 9.9}, {"DayOfWeek": 2, "Month": 5, "Hour": 12, "District": 862, "Price": 602.0, "Duration": 17, "Length": 6.8}, {"DayOfWeek": 2, "Month": 5, "Hour": 12, "District": 762, "Price": 613.0, "Duration": 24, "Length": 9.9}, {"DayOfWeek": 2, "Month": 5, "Hour": 12, "District": 292, "Price": 299.0, "Duration": 38, "Length": 22.4}, {"DayOfWeek": 2, "Month": 5, "Hour": 12, "District": 500, "Price": 492.0, "Duration": 23, "Length": 6.1}, {"DayOfWeek": 2, "Month": 5, "Hour": 12, "District": 113, "Price": 534.0, "Duration": 17, "Length": 7.0}, {"DayOfWeek": 2, "Month": 5, "Hour": 12, "District": 884, "Price": 639.0, "Duration": 15, "Length": 7.4}, {"DayOfWeek": 2, "Month": 5, "Hour": 12, "District": 836, "Price": 1209.0, "Duration": 36, "Length": 27.1}, {"DayOfWeek": 2, "Month": 5, "Hour": 12, "District": 351, "Price": 398.0, "Duration": 8, "Length": 4.6}, {"DayOfWeek": 2, "Month": 5, "Hour": 12, "District": 854, "Price": 628.0, "Duration": 36, "Length": 8.6}, {"DayOfWeek": 2, "Month": 5, "Hour": 12, "District": 226, "Price": 241.0, "Duration": 6, "Length": 1.95}, {"DayOfWeek": 2, "Month": 5, "Hour": 12, "District": 804, "Price": 877.0, "Duration": 30, "Length": 15.3}, {"DayOfWeek": 2, "Month": 5, "Hour": 12, "District": 508, "Price": 555.0, "Duration": 21, "Length": 7.0}, {"DayOfWeek": 2, "Month": 5, "Hour": 12, "District": 328, "Price": 634.0, "Duration": 31, "Length": 10.3}, {"DayOfWeek": 2, "Month": 5, "Hour": 12, "District": 202, "Price": 906.0, "Duration": 32, "Length": 16.0}, {"DayOfWeek": 2, "Month": 5, "Hour": 12, "District": 525, "Price": 884.0, "Duration": 22, "Length": 10.2}, {"DayOfWeek": 2, "Month": 5, "Hour": 12, "District": 21, "Price": 771.0, "Duration": 27, "Length": 10.8}, {"DayOfWeek": 2, "Month": 5, "Hour": 12, "District": 798, "Price": 369.0, "Duration": 35, "Length": 31.0}, {"DayOfWeek": 2, "Month": 5, "Hour": 12, "District": 688, "Price": 779.0, "Duration": 27, "Length": 10.8}, {"DayOfWeek": 2, "Month": 5, "Hour": 12, "District": 963, "Price": 580.0, "Duration": 18, "Length": 6.8}, {"DayOfWeek": 2, "Month": 5, "Hour": 12, "District": 383, "Price": 1418.0, "Duration": 29, "Length": 26.5}, {"DayOfWeek": 2, "Month": 5, "Hour": 12, "District": 871, "Price": 840.0, "Duration": 27, "Length": 12.0}, {"DayOfWeek": 2, "Month": 5, "Hour": 12, "District": 322, "Price": 571.0, "Duration": 17, "Length": 10.5}, {"DayOfWeek": 2, "Month": 5, "Hour": 12, "District": 636, "Price": 862.0, "Duration": 38, "Length": 12.7}, {"DayOfWeek": 2, "Month": 5, "Hour": 12, "District": 616, "Price": 748.0, "Duration": 20, "Length": 7.7}, {"DayOfWeek": 2, "Month": 5, "Hour": 12, "District": 711, "Price": 568.0, "Duration": 13, "Length": 5.6}, {"DayOfWeek": 2, "Month": 5, "Hour": 12, "District": 966, "Price": 387.0, "Duration": 13, "Length": 3.5}, {"DayOfWeek": 2, "Month": 5, "Hour": 12, "District": 445, "Price": 602.0, "Duration": 17, "Length": 6.9}, {"DayOfWeek": 2, "Month": 5, "Hour": 12, "District": 259, "Price": 405.0, "Duration": 14, "Length": 5.5}, {"DayOfWeek": 2, "Month": 5, "Hour": 12, "District": 382, "Price": 401.0, "Duration": 14, "Length": 4.5}, {"DayOfWeek": 2, "Month": 5, "Hour": 12, "District": 13, "Price": 769.0, "Duration": 41, "Length": 11.7}, {"DayOfWeek": 2, "Month": 5, "Hour": 12, "District": 795, "Price": 602.0, "Duration": 17, "Length": 5.0}, {"DayOfWeek": 2, "Month": 5, "Hour": 12, "District": 46, "Price": 289.0, "Duration": 30, "Length": 26.7}, {"DayOfWeek": 2, "Month": 5, "Hour": 12, "District": 102, "Price": 625.0, "Duration": 18, "Length": 5.7}, {"DayOfWeek": 2, "Month": 5, "Hour": 12, "District": 701, "Price": 927.0, "Duration": 31, "Length": 25.2}, {"DayOfWeek": 2, "Month": 5, "Hour": 12, "District": 454, "Price": 318.0, "Duration": 12, "Length": 5.0}, {"DayOfWeek": 2, "Month": 5, "Hour": 12, "District": 450, "Price": 409.0, "Duration": 14, "Length": 4.9}, {"DayOfWeek": 2, "Month": 5, "Hour": 12, "District": 72, "Price": 695.0, "Duration": 24, "Length": 12.3}, {"DayOfWeek": 2, "Month": 5, "Hour": 12, "District": 831, "Price": 775.0, "Duration": 29, "Length": 13.7}, {"DayOfWeek": 2, "Month": 5, "Hour": 12, "District": 994, "Price": 1183.0, "Duration": 41, "Length": 23.7}, {"DayOfWeek": 2, "Month": 5, "Hour": 12, "District": 760, "Price": 787.0, "Duration": 26, "Length": 15.9}, {"DayOfWeek": 2, "Month": 5, "Hour": 12, "District": 442, "Price": 816.0, "Duration": 26, "Length": 23.2}, {"DayOfWeek": 2, "Month": 5, "Hour": 12, "District": 685, "Price": 1142.0, "Duration": 33, "Length": 28.3}, {"DayOfWeek": 2, "Month": 5, "Hour": 12, "District": 353, "Price": 662.0, "Duration": 25, "Length": 9.3}, {"DayOfWeek": 2, "Month": 5, "Hour": 12, "District": 585, "Price": 309.0, "Duration": 40, "Length": 28.2}, {"DayOfWeek": 2, "Month": 5, "Hour": 12, "District": 598, "Price": 349.0, "Duration": 27, "Length": 20.9}, {"DayOfWeek": 2, "Month": 5, "Hour": 12, "District": 526, "Price": 279.0, "Duration": 28, "Length": 21.1}, {"DayOfWeek": 2, "Month": 5, "Hour": 12, "District": 765, "Price": 299.0, "Duration": 42, "Length": 25.8}, {"DayOfWeek": 2, "Month": 5, "Hour": 12, "District": 657, "Price": 309.0, "Duration": 31, "Length": 25.8}, {"DayOfWeek": 2, "Month": 5, "Hour": 12, "District": 894, "Price": 854.0, "Duration": 39, "Length": 12.5}, {"DayOfWeek": 2, "Month": 5, "Hour": 12, "District": 877, "Price": 278.0, "Duration": 10, "Length": 4.1}, {"DayOfWeek": 2, "Month": 5, "Hour": 12, "District": 727, "Price": 782.0, "Duration": 38, "Length": 17.9}, {"DayOfWeek": 2, "Month": 5, "Hour": 12, "District": 864, "Price": 1364.0, "Duration": 34, "Length": 26.1}, {"DayOfWeek": 2, "Month": 5, "Hour": 12, "District": 870, "Price": 696.0, "Duration": 28, "Length": 15.2}, {"DayOfWeek": 2, "Month": 5, "Hour": 12, "District": 641, "Price": 702.0, "Duration": 18, "Length": 6.5}, {"DayOfWeek": 2, "Month": 5, "Hour": 12, "District": 374, "Price": 476.0, "Duration": 29, "Length": 6.3}, {"DayOfWeek": 2, "Month": 5, "Hour": 12, "District": 838, "Price": 447.0, "Duration": 26, "Length": 9.3}, {"DayOfWeek": 2, "Month": 5, "Hour": 12, "District": 102, "Price": 666.0, "Duration": 23, "Length": 17.2}, {"DayOfWeek": 2, "Month": 5, "Hour": 12, "District": 75, "Price": 746.0, "Duration": 37, "Length": 8.5}, {"DayOfWeek": 2, "Month": 5, "Hour": 12, "District": 594, "Price": 721.0, "Duration": 25, "Length": 12.7}, {"DayOfWeek": 2, "Month": 5, "Hour": 12, "District": 715, "Price": 397.0, "Duration": 17, "Length": 7.2}, {"DayOfWeek": 2, "Month": 5, "Hour": 12, "District": 131, "Price": 610.0, "Duration": 18, "Length": 22.0}, {"DayOfWeek": 2, "Month": 5, "Hour": 12, "District": 153, "Price": 444.0, "Duration": 13, "Length": 5.7}, {"DayOfWeek": 2, "Month": 5, "Hour": 12, "District": 901, "Price": 906.0, "Duration": 29, "Length": 16.3}, {"DayOfWeek": 2, "Month": 5, "Hour": 12, "District": 891, "Price": 329.0, "Duration": 4, "Length": 1.6}, {"DayOfWeek": 2, "Month": 5, "Hour": 12, "District": 103, "Price": 316.0, "Duration": 10, "Length": 2.26}, {"DayOfWeek": 2, "Month": 5, "Hour": 12, "District": 355, "Price": 759.0, "Duration": 27, "Length": 8.8}, {"DayOfWeek": 2, "Month": 5, "Hour": 12, "District": 43, "Price": 842.0, "Duration": 33, "Length": 12.7}, {"DayOfWeek": 2, "Month": 5, "Hour": 12, "District": 858, "Price": 381.0, "Duration": 5, "Length": 1.86}, {"DayOfWeek": 2, "Month": 5, "Hour": 12, "District": 719, "Price": 736.0, "Duration": 24, "Length": 8.6}, {"DayOfWeek": 2, "Month": 5, "Hour": 12, "District": 372, "Price": 582.0, "Duration": 16, "Length": 7.2}, {"DayOfWeek": 2, "Month": 5, "Hour": 12, "District": 36, "Price": 684.0, "Duration": 34, "Length": 9.0},{"DayOfWeek": 2, "Month": 5, "Hour": 13, "District": 292, "Price": 259.0, "Duration": 38, "Length": 25.7}, {"DayOfWeek": 2, "Month": 5, "Hour": 13, "District": 113, "Price": 499.0, "Duration": 17, "Length": 7.0}, {"DayOfWeek": 2, "Month": 5, "Hour": 13, "District": 153, "Price": 467.0, "Duration": 13, "Length": 5.7}, {"DayOfWeek": 2, "Month": 5, "Hour": 13, "District": 594, "Price": 595.0, "Duration": 21, "Length": 12.7}, {"DayOfWeek": 2, "Month": 5, "Hour": 13, "District": 75, "Price": 767.0, "Duration": 31, "Length": 7.6}, {"DayOfWeek": 2, "Month": 5, "Hour": 13, "District": 525, "Price": 935.0, "Duration": 28, "Length": 10.2}, {"DayOfWeek": 2, "Month": 5, "Hour": 13, "District": 274, "Price": 764.0, "Duration": 20, "Length": 17.6}, {"DayOfWeek": 2, "Month": 5, "Hour": 13, "District": 374, "Price": 700.0, "Duration": 39, "Length": 5.6}, {"DayOfWeek": 2, "Month": 5, "Hour": 13, "District": 454, "Price": 425.0, "Duration": 12, "Length": 5.0}, {"DayOfWeek": 2, "Month": 5, "Hour": 13, "District": 145, "Price": 858.0, "Duration": 31, "Length": 13.3}, {"DayOfWeek": 2, "Month": 5, "Hour": 13, "District": 102, "Price": 492.0, "Duration": 17, "Length": 5.7}, {"DayOfWeek": 2, "Month": 5, "Hour": 13, "District": 858, "Price": 361.0, "Duration": 5, "Length": 1.86}, {"DayOfWeek": 2, "Month": 5, "Hour": 13, "District": 701, "Price": 1171.0, "Duration": 34, "Length": 25.2}, {"DayOfWeek": 2, "Month": 5, "Hour": 13, "District": 325, "Price": 179.0, "Duration": 46, "Length": 26.1}, {"DayOfWeek": 2, "Month": 5, "Hour": 13, "District": 693, "Price": 894.0, "Duration": 32, "Length": 16.3}, {"DayOfWeek": 2, "Month": 5, "Hour": 13, "District": 541, "Price": 938.0, "Duration": 22, "Length": 22.1}, {"DayOfWeek": 2, "Month": 5, "Hour": 13, "District": 442, "Price": 822.0, "Duration": 29, "Length": 21.1}, {"DayOfWeek": 2, "Month": 5, "Hour": 13, "District": 450, "Price": 383.0, "Duration": 14, "Length": 4.9}, {"DayOfWeek": 2, "Month": 5, "Hour": 13, "District": 760, "Price": 780.0, "Duration": 29, "Length": 16.4}, {"DayOfWeek": 2, "Month": 5, "Hour": 13, "District": 641, "Price": 650.0, "Duration": 18, "Length": 6.5}, {"DayOfWeek": 2, "Month": 5, "Hour": 13, "District": 765, "Price": 219.0, "Duration": 40, "Length": 25.8}, {"DayOfWeek": 2, "Month": 5, "Hour": 13, "District": 383, "Price": 1380.0, "Duration": 27, "Length": 26.5}, {"DayOfWeek": 2, "Month": 5, "Hour": 13, "District": 115, "Price": 859.0, "Duration": 36, "Length": 14.0}, {"DayOfWeek": 2, "Month": 5, "Hour": 13, "District": 427, "Price": 369.0, "Duration": 39, "Length": 24.2}, {"DayOfWeek": 2, "Month": 5, "Hour": 13, "District": 616, "Price": 710.0, "Duration": 21, "Length": 7.7}, {"DayOfWeek": 2, "Month": 5, "Hour": 13, "District": 94, "Price": 624.0, "Duration": 23, "Length": 10.3}, {"DayOfWeek": 2, "Month": 5, "Hour": 13, "District": 220, "Price": 770.0, "Duration": 27, "Length": 10.0}, {"DayOfWeek": 2, "Month": 5, "Hour": 13, "District": 457, "Price": 514.0, "Duration": 12, "Length": 4.9}, {"DayOfWeek": 2, "Month": 5, "Hour": 13, "District": 870, "Price": 857.0, "Duration": 29, "Length": 15.2}, {"DayOfWeek": 2, "Month": 5, "Hour": 13, "District": 29, "Price": 479.0, "Duration": 25, "Length": 18.1}, {"DayOfWeek": 2, "Month": 5, "Hour": 13, "District": 634, "Price": 544.0, "Duration": 13, "Length": 5.9}, {"DayOfWeek": 2, "Month": 5, "Hour": 13, "District": 964, "Price": 789.0, "Duration": 45, "Length": 10.9}, {"DayOfWeek": 2, "Month": 5, "Hour": 13, "District": 798, "Price": 369.0, "Duration": 37, "Length": 31.0}, {"DayOfWeek": 2, "Month": 5, "Hour": 13, "District": 966, "Price": 552.0, "Duration": 13, "Length": 3.3}, {"DayOfWeek": 2, "Month": 5, "Hour": 13, "District": 372, "Price": 398.0, "Duration": 16, "Length": 7.2}, {"DayOfWeek": 2, "Month": 5, "Hour": 13, "District": 33, "Price": 735.0, "Duration": 22, "Length": 8.9}, {"DayOfWeek": 2, "Month": 5, "Hour": 13, "District": 894, "Price": 868.0, "Duration": 37, "Length": 11.8}, {"DayOfWeek": 2, "Month": 5, "Hour": 13, "District": 21, "Price": 736.0, "Duration": 28, "Length": 10.8}, {"DayOfWeek": 2, "Month": 5, "Hour": 13, "District": 43, "Price": 881.0, "Duration": 34, "Length": 12.7}, {"DayOfWeek": 2, "Month": 5, "Hour": 13, "District": 891, "Price": 369.0, "Duration": 4, "Length": 1.6}, {"DayOfWeek": 2, "Month": 5, "Hour": 13, "District": 508, "Price": 533.0, "Duration": 20, "Length": 7.3}, {"DayOfWeek": 2, "Month": 5, "Hour": 13, "District": 103, "Price": 374.0, "Duration": 9, "Length": 2.26}, {"DayOfWeek": 2, "Month": 5, "Hour": 13, "District": 352, "Price": 752.0, "Duration": 37, "Length": 37.0}, {"DayOfWeek": 2, "Month": 5, "Hour": 13, "District": 565, "Price": 409.0, "Duration": 9, "Length": 3.6}, {"DayOfWeek": 2, "Month": 5, "Hour": 13, "District": 102, "Price": 1003.0, "Duration": 23, "Length": 17.2}, {"DayOfWeek": 2, "Month": 5, "Hour": 13, "District": 270, "Price": 409.0, "Duration": 36, "Length": 30.0}, {"DayOfWeek": 2, "Month": 5, "Hour": 13, "District": 733, "Price": 678.0, "Duration": 21, "Length": 8.6}, {"DayOfWeek": 2, "Month": 5, "Hour": 13, "District": 657, "Price": 369.0, "Duration": 33, "Length": 25.7}, {"DayOfWeek": 2, "Month": 5, "Hour": 13, "District": 598, "Price": 429.0, "Duration": 29, "Length": 20.9}, {"DayOfWeek": 2, "Month": 5, "Hour": 13, "District": 259, "Price": 451.0, "Duration": 15, "Length": 5.5}, {"DayOfWeek": 2, "Month": 5, "Hour": 13, "District": 145, "Price": 1155.0, "Duration": 33, "Length": 17.8}, {"DayOfWeek": 2, "Month": 5, "Hour": 13, "District": 688, "Price": 749.0, "Duration": 27, "Length": 10.4}, {"DayOfWeek": 2, "Month": 5, "Hour": 13, "District": 427, "Price": 627.0, "Duration": 23, "Length": 11.0}, {"DayOfWeek": 2, "Month": 5, "Hour": 13, "District": 622, "Price": 621.0, "Duration": 21, "Length": 6.1}, {"DayOfWeek": 2, "Month": 5, "Hour": 13, "District": 685, "Price": 1005.0, "Duration": 31, "Length": 22.1}, {"DayOfWeek": 2, "Month": 5, "Hour": 13, "District": 234, "Price": 369.0, "Duration": 45, "Length": 23.9}, {"DayOfWeek": 2, "Month": 5, "Hour": 13, "District": 854, "Price": 630.0, "Duration": 29, "Length": 11.2}, {"DayOfWeek": 2, "Month": 5, "Hour": 13, "District": 884, "Price": 670.0, "Duration": 16, "Length": 7.4}, {"DayOfWeek": 2, "Month": 5, "Hour": 13, "District": 417, "Price": 553.0, "Duration": 18, "Length": 4.3}, {"DayOfWeek": 2, "Month": 5, "Hour": 13, "District": 862, "Price": 548.0, "Duration": 16, "Length": 6.8}, {"DayOfWeek": 2, "Month": 5, "Hour": 13, "District": 963, "Price": 486.0, "Duration": 18, "Length": 6.8}, {"DayOfWeek": 2, "Month": 5, "Hour": 13, "District": 719, "Price": 451.0, "Duration": 22, "Length": 8.5}, {"DayOfWeek": 2, "Month": 5, "Hour": 13, "District": 90, "Price": 1298.0, "Duration": 36, "Length": 26.0}, {"DayOfWeek": 2, "Month": 5, "Hour": 13, "District": 877, "Price": 369.0, "Duration": 10, "Length": 3.3}, {"DayOfWeek": 2, "Month": 5, "Hour": 13, "District": 477, "Price": 645.0, "Duration": 26, "Length": 10.9}, {"DayOfWeek": 2, "Month": 5, "Hour": 13, "District": 382, "Price": 515.0, "Duration": 15, "Length": 4.5}, {"DayOfWeek": 2, "Month": 5, "Hour": 13, "District": 795, "Price": 401.0, "Duration": 17, "Length": 5.0}, {"DayOfWeek": 2, "Month": 5, "Hour": 13, "District": 871, "Price": 734.0, "Duration": 28, "Length": 11.7}, {"DayOfWeek": 2, "Month": 5, "Hour": 13, "District": 226, "Price": 259.0, "Duration": 6, "Length": 1.95}, {"DayOfWeek": 2, "Month": 5, "Hour": 13, "District": 419, "Price": 831.0, "Duration": 27, "Length": 12.7}, {"DayOfWeek": 2, "Month": 5, "Hour": 13, "District": 762, "Price": 667.0, "Duration": 23, "Length": 9.9}, {"DayOfWeek": 2, "Month": 5, "Hour": 13, "District": 40, "Price": 803.0, "Duration": 22, "Length": 5.7}, {"DayOfWeek": 2, "Month": 5, "Hour": 13, "District": 636, "Price": 808.0, "Duration": 38, "Length": 12.8}, {"DayOfWeek": 2, "Month": 5, "Hour": 13, "District": 994, "Price": 920.0, "Duration": 40, "Length": 19.3}, {"DayOfWeek": 2, "Month": 5, "Hour": 13, "District": 834, "Price": 701.0, "Duration": 25, "Length": 8.8}, {"DayOfWeek": 2, "Month": 5, "Hour": 13, "District": 727, "Price": 856.0, "Duration": 43, "Length": 17.9}, {"DayOfWeek": 2, "Month": 5, "Hour": 13, "District": 164, "Price": 636.0, "Duration": 19, "Length": 11.9}, {"DayOfWeek": 2, "Month": 5, "Hour": 13, "District": 271, "Price": 535.0, "Duration": 16, "Length": 7.4}, {"DayOfWeek": 2, "Month": 5, "Hour": 13, "District": 353, "Price": 552.0, "Duration": 26, "Length": 9.3}, {"DayOfWeek": 2, "Month": 5, "Hour": 13, "District": 585, "Price": 369.0, "Duration": 40, "Length": 28.2}, {"DayOfWeek": 2, "Month": 5, "Hour": 13, "District": 707, "Price": 660.0, "Duration": 27, "Length": 9.7}, {"DayOfWeek": 2, "Month": 5, "Hour": 13, "District": 36, "Price": 756.0, "Duration": 40, "Length": 7.5}, {"DayOfWeek": 2, "Month": 5, "Hour": 13, "District": 382, "Price": 689.0, "Duration": 25, "Length": 9.6}, {"DayOfWeek": 2, "Month": 5, "Hour": 13, "District": 362, "Price": 344.0, "Duration": 7, "Length": 2.1}, {"DayOfWeek": 2, "Month": 5, "Hour": 13, "District": 46, "Price": 269.0, "Duration": 34, "Length": 26.7}, {"DayOfWeek": 2, "Month": 5, "Hour": 13, "District": 864, "Price": 1155.0, "Duration": 35, "Length": 26.1}, {"DayOfWeek": 2, "Month": 5, "Hour": 13, "District": 351, "Price": 362.0, "Duration": 9, "Length": 4.6}, {"DayOfWeek": 2, "Month": 5, "Hour": 13, "District": 13, "Price": 861.0, "Duration": 34, "Length": 9.4}, {"DayOfWeek": 2, "Month": 5, "Hour": 13, "District": 356, "Price": 495.0, "Duration": 16, "Length": 5.3}, {"DayOfWeek": 2, "Month": 5, "Hour": 13, "District": 313, "Price": 409.0, "Duration": 35, "Length": 20.4}, {"DayOfWeek": 2, "Month": 5, "Hour": 13, "District": 804, "Price": 868.0, "Duration": 27, "Length": 15.3}, {"DayOfWeek": 2, "Month": 5, "Hour": 13, "District": 526, "Price": 279.0, "Duration": 30, "Length": 20.5}, {"DayOfWeek": 2, "Month": 5, "Hour": 13, "District": 897, "Price": 575.0, "Duration": 17, "Length": 7.9}, {"DayOfWeek": 2, "Month": 5, "Hour": 13, "District": 445, "Price": 601.0, "Duration": 17, "Length": 6.9}, {"DayOfWeek": 2, "Month": 5, "Hour": 13, "District": 385, "Price": 369.0, "Duration": 33, "Length": 20.7}, {"DayOfWeek": 2, "Month": 5, "Hour": 13, "District": 838, "Price": 584.0, "Duration": 24, "Length": 9.6}, {"DayOfWeek": 2, "Month": 5, "Hour": 13, "District": 355, "Price": 749.0, "Duration": 25, "Length": 9.4}, {"DayOfWeek": 2, "Month": 5, "Hour": 13, "District": 72, "Price": 690.0, "Duration": 23, "Length": 12.3}, {"DayOfWeek": 2, "Month": 5, "Hour": 13, "District": 131, "Price": 1019.0, "Duration": 19, "Length": 22.0}, {"DayOfWeek": 2, "Month": 5, "Hour": 13, "District": 174, "Price": 701.0, "Duration": 26, "Length": 16.3}, {"DayOfWeek": 2, "Month": 5, "Hour": 13, "District": 328, "Price": 633.0, "Duration": 27, "Length": 10.3}, {"DayOfWeek": 2, "Month": 5, "Hour": 13, "District": 831, "Price": 802.0, "Duration": 29, "Length": 13.7}, {"DayOfWeek": 2, "Month": 5, "Hour": 13, "District": 186, "Price": 672.0, "Duration": 24, "Length": 10.0}, {"DayOfWeek": 2, "Month": 5, "Hour": 13, "District": 195, "Price": 239.0, "Duration": 39, "Length": 28.0}, {"DayOfWeek": 2, "Month": 5, "Hour": 13, "District": 500, "Price": 807.0, "Duration": 25, "Length": 6.1}, {"DayOfWeek": 2, "Month": 5, "Hour": 13, "District": 711, "Price": 517.0, "Duration": 13, "Length": 5.6}, {"DayOfWeek": 2, "Month": 5, "Hour": 13, "District": 202, "Price": 920.0, "Duration": 36, "Length": 16.5}, {"DayOfWeek": 2, "Month": 5, "Hour": 13, "District": 449, "Price": 604.0, "Duration": 19, "Length": 6.7}, {"DayOfWeek": 2, "Month": 5, "Hour": 13, "District": 732, "Price": 575.0, "Duration": 19, "Length": 10.2}, {"DayOfWeek": 2, "Month": 5, "Hour": 13, "District": 735, "Price": 661.0, "Duration": 18, "Length": 7.6},{"DayOfWeek": 2, "Month": 5, "Hour": 14, "District": 838, "Price": 554.0, "Duration": 25, "Length": 9.3}, {"DayOfWeek": 2, "Month": 5, "Hour": 14, "District": 292, "Price": 329.0, "Duration": 39, "Length": 22.3}, {"DayOfWeek": 2, "Month": 5, "Hour": 14, "District": 270, "Price": 369.0, "Duration": 34, "Length": 28.6}, {"DayOfWeek": 2, "Month": 5, "Hour": 14, "District": 417, "Price": 530.0, "Duration": 20, "Length": 4.3}, {"DayOfWeek": 2, "Month": 5, "Hour": 14, "District": 500, "Price": 854.0, "Duration": 29, "Length": 6.1}, {"DayOfWeek": 2, "Month": 5, "Hour": 14, "District": 13, "Price": 733.0, "Duration": 34, "Length": 9.4}, {"DayOfWeek": 2, "Month": 5, "Hour": 14, "District": 701, "Price": 1342.0, "Duration": 31, "Length": 25.2}, {"DayOfWeek": 2, "Month": 5, "Hour": 14, "District": 762, "Price": 487.0, "Duration": 23, "Length": 10.1}, {"DayOfWeek": 2, "Month": 5, "Hour": 14, "District": 795, "Price": 559.0, "Duration": 17, "Length": 5.0}, {"DayOfWeek": 2, "Month": 5, "Hour": 14, "District": 356, "Price": 390.0, "Duration": 16, "Length": 5.1}, {"DayOfWeek": 2, "Month": 5, "Hour": 14, "District": 274, "Price": 862.0, "Duration": 18, "Length": 17.6}, {"DayOfWeek": 2, "Month": 5, "Hour": 14, "District": 220, "Price": 755.0, "Duration": 27, "Length": 10.0}, {"DayOfWeek": 2, "Month": 5, "Hour": 14, "District": 195, "Price": 259.0, "Duration": 39, "Length": 28.1}, {"DayOfWeek": 2, "Month": 5, "Hour": 14, "District": 22, "Price": 548.0, "Duration": 17, "Length": 6.6}, {"DayOfWeek": 2, "Month": 5, "Hour": 14, "District": 351, "Price": 308.0, "Duration": 8, "Length": 4.6}, {"DayOfWeek": 2, "Month": 5, "Hour": 14, "District": 715, "Price": 459.0, "Duration": 18, "Length": 7.2}, {"DayOfWeek": 2, "Month": 5, "Hour": 14, "District": 75, "Price": 540.0, "Duration": 30, "Length": 7.6}, {"DayOfWeek": 2, "Month": 5, "Hour": 14, "District": 29, "Price": 539.0, "Duration": 28, "Length": 18.1}, {"DayOfWeek": 2, "Month": 5, "Hour": 14, "District": 449, "Price": 611.0, "Duration": 26, "Length": 9.1}, {"DayOfWeek": 2, "Month": 5, "Hour": 14, "District": 541, "Price": 1042.0, "Duration": 22, "Length": 22.1}, {"DayOfWeek": 2, "Month": 5, "Hour": 14, "District": 525, "Price": 608.0, "Duration": 18, "Length": 10.2}, {"DayOfWeek": 2, "Month": 5, "Hour": 14, "District": 901, "Price": 917.0, "Duration": 28, "Length": 23.1}, {"DayOfWeek": 2, "Month": 5, "Hour": 14, "District": 145, "Price": 808.0, "Duration": 33, "Length": 17.8}, {"DayOfWeek": 2, "Month": 5, "Hour": 14, "District": 234, "Price": 369.0, "Duration": 45, "Length": 24.1}, {"DayOfWeek": 2, "Month": 5, "Hour": 14, "District": 450, "Price": 410.0, "Duration": 14, "Length": 4.9}, {"DayOfWeek": 2, "Month": 5, "Hour": 14, "District": 897, "Price": 569.0, "Duration": 21, "Length": 7.0}, {"DayOfWeek": 2, "Month": 5, "Hour": 14, "District": 454, "Price": 416.0, "Duration": 12, "Length": 5.0}, {"DayOfWeek": 2, "Month": 5, "Hour": 14, "District": 353, "Price": 708.0, "Duration": 29, "Length": 9.3}, {"DayOfWeek": 2, "Month": 5, "Hour": 14, "District": 174, "Price": 831.0, "Duration": 27, "Length": 16.5}, {"DayOfWeek": 2, "Month": 5, "Hour": 14, "District": 804, "Price": 741.0, "Duration": 28, "Length": 15.3}, {"DayOfWeek": 2, "Month": 5, "Hour": 14, "District": 385, "Price": 309.0, "Duration": 36, "Length": 20.7}, {"DayOfWeek": 2, "Month": 5, "Hour": 14, "District": 226, "Price": 239.0, "Duration": 6, "Length": 1.95}, {"DayOfWeek": 2, "Month": 5, "Hour": 14, "District": 90, "Price": 1166.0, "Duration": 34, "Length": 27.3}, {"DayOfWeek": 2, "Month": 5, "Hour": 14, "District": 362, "Price": 365.0, "Duration": 7, "Length": 2.1}, {"DayOfWeek": 2, "Month": 5, "Hour": 14, "District": 719, "Price": 641.0, "Duration": 23, "Length": 8.6}, {"DayOfWeek": 2, "Month": 5, "Hour": 14, "District": 508, "Price": 464.0, "Duration": 21, "Length": 7.1}, {"DayOfWeek": 2, "Month": 5, "Hour": 14, "District": 164, "Price": 584.0, "Duration": 19, "Length": 11.9}, {"DayOfWeek": 2, "Month": 5, "Hour": 14, "District": 419, "Price": 821.0, "Duration": 29, "Length": 13.8}, {"DayOfWeek": 2, "Month": 5, "Hour": 14, "District": 102, "Price": 481.0, "Duration": 19, "Length": 5.7}, {"DayOfWeek": 2, "Month": 5, "Hour": 14, "District": 636, "Price": 895.0, "Duration": 41, "Length": 12.7}, {"DayOfWeek": 2, "Month": 5, "Hour": 14, "District": 693, "Price": 918.0, "Duration": 32, "Length": 16.3}, {"DayOfWeek": 2, "Month": 5, "Hour": 14, "District": 831, "Price": 734.0, "Duration": 34, "Length": 11.0}, {"DayOfWeek": 2, "Month": 5, "Hour": 14, "District": 765, "Price": 369.0, "Duration": 41, "Length": 21.9}, {"DayOfWeek": 2, "Month": 5, "Hour": 14, "District": 836, "Price": 1173.0, "Duration": 33, "Length": 29.8}, {"DayOfWeek": 2, "Month": 5, "Hour": 14, "District": 735, "Price": 588.0, "Duration": 18, "Length": 7.1}, {"DayOfWeek": 2, "Month": 5, "Hour": 14, "District": 445, "Price": 581.0, "Duration": 19, "Length": 6.9}, {"DayOfWeek": 2, "Month": 5, "Hour": 14, "District": 733, "Price": 532.0, "Duration": 21, "Length": 8.6}, {"DayOfWeek": 2, "Month": 5, "Hour": 14, "District": 984, "Price": 764.0, "Duration": 33, "Length": 6.4}, {"DayOfWeek": 2, "Month": 5, "Hour": 14, "District": 618, "Price": 257.0, "Duration": 7, "Length": 3.4}, {"DayOfWeek": 2, "Month": 5, "Hour": 14, "District": 103, "Price": 391.0, "Duration": 8, "Length": 2.26}, {"DayOfWeek": 2, "Month": 5, "Hour": 14, "District": 94, "Price": 491.0, "Duration": 23, "Length": 10.3}, {"DayOfWeek": 2, "Month": 5, "Hour": 14, "District": 372, "Price": 541.0, "Duration": 16, "Length": 7.2}, {"DayOfWeek": 2, "Month": 5, "Hour": 14, "District": 43, "Price": 850.0, "Duration": 37, "Length": 12.7}, {"DayOfWeek": 2, "Month": 5, "Hour": 14, "District": 634, "Price": 441.0, "Duration": 14, "Length": 5.9}, {"DayOfWeek": 2, "Month": 5, "Hour": 14, "District": 382, "Price": 774.0, "Duration": 25, "Length": 9.4}, {"DayOfWeek": 2, "Month": 5, "Hour": 14, "District": 352, "Price": 728.0, "Duration": 34, "Length": 37.0}, {"DayOfWeek": 2, "Month": 5, "Hour": 14, "District": 328, "Price": 697.0, "Duration": 34, "Length": 10.3}, {"DayOfWeek": 2, "Month": 5, "Hour": 14, "District": 21, "Price": 751.0, "Duration": 27, "Length": 10.8}, {"DayOfWeek": 2, "Month": 5, "Hour": 14, "District": 707, "Price": 673.0, "Duration": 26, "Length": 10.0}, {"DayOfWeek": 2, "Month": 5, "Hour": 14, "District": 565, "Price": 313.0, "Duration": 9, "Length": 3.6}, {"DayOfWeek": 2, "Month": 5, "Hour": 14, "District": 355, "Price": 708.0, "Duration": 26, "Length": 9.4}, {"DayOfWeek": 2, "Month": 5, "Hour": 14, "District": 322, "Price": 545.0, "Duration": 16, "Length": 10.5}, {"DayOfWeek": 2, "Month": 5, "Hour": 14, "District": 622, "Price": 614.0, "Duration": 20, "Length": 6.1}, {"DayOfWeek": 2, "Month": 5, "Hour": 14, "District": 862, "Price": 621.0, "Duration": 16, "Length": 6.8}, {"DayOfWeek": 2, "Month": 5, "Hour": 14, "District": 427, "Price": 710.0, "Duration": 24, "Length": 13.3}, {"DayOfWeek": 2, "Month": 5, "Hour": 14, "District": 374, "Price": 568.0, "Duration": 24, "Length": 5.4}, {"DayOfWeek": 2, "Month": 5, "Hour": 14, "District": 131, "Price": 1139.0, "Duration": 18, "Length": 22.0}, {"DayOfWeek": 2, "Month": 5, "Hour": 14, "District": 732, "Price": 645.0, "Duration": 20, "Length": 10.2}, {"DayOfWeek": 2, "Month": 5, "Hour": 14, "District": 641, "Price": 519.0, "Duration": 18, "Length": 6.5}, {"DayOfWeek": 2, "Month": 5, "Hour": 14, "District": 271, "Price": 439.0, "Duration": 15, "Length": 7.4}, {"DayOfWeek": 2, "Month": 5, "Hour": 14, "District": 40, "Price": 763.0, "Duration": 20, "Length": 5.4}, {"DayOfWeek": 2, "Month": 5, "Hour": 14, "District": 598, "Price": 329.0, "Duration": 30, "Length": 20.9}, {"DayOfWeek": 2, "Month": 5, "Hour": 14, "District": 877, "Price": 230.0, "Duration": 10, "Length": 4.1}, {"DayOfWeek": 2, "Month": 5, "Hour": 14, "District": 864, "Price": 930.0, "Duration": 31, "Length": 26.1}, {"DayOfWeek": 2, "Month": 5, "Hour": 14, "District": 870, "Price": 883.0, "Duration": 32, "Length": 15.2}, {"DayOfWeek": 2, "Month": 5, "Hour": 14, "District": 834, "Price": 811.0, "Duration": 24, "Length": 8.8}, {"DayOfWeek": 2, "Month": 5, "Hour": 14, "District": 760, "Price": 896.0, "Duration": 30, "Length": 15.9}, {"DayOfWeek": 2, "Month": 5, "Hour": 14, "District": 72, "Price": 739.0, "Duration": 24, "Length": 12.3}, {"DayOfWeek": 2, "Month": 5, "Hour": 14, "District": 153, "Price": 434.0, "Duration": 13, "Length": 5.5}, {"DayOfWeek": 2, "Month": 5, "Hour": 14, "District": 711, "Price": 452.0, "Duration": 13, "Length": 5.6}, {"DayOfWeek": 2, "Month": 5, "Hour": 14, "District": 657, "Price": 279.0, "Duration": 31, "Length": 25.7}, {"DayOfWeek": 2, "Month": 5, "Hour": 14, "District": 202, "Price": 991.0, "Duration": 32, "Length": 19.2}, {"DayOfWeek": 2, "Month": 5, "Hour": 14, "District": 966, "Price": 630.0, "Duration": 13, "Length": 3.3}, {"DayOfWeek": 2, "Month": 5, "Hour": 14, "District": 46, "Price": 259.0, "Duration": 29, "Length": 26.7}, {"DayOfWeek": 2, "Month": 5, "Hour": 14, "District": 383, "Price": 1277.0, "Duration": 25, "Length": 26.5}, {"DayOfWeek": 2, "Month": 5, "Hour": 14, "District": 585, "Price": 309.0, "Duration": 42, "Length": 28.2}, {"DayOfWeek": 2, "Month": 5, "Hour": 14, "District": 616, "Price": 662.0, "Duration": 20, "Length": 7.7}, {"DayOfWeek": 2, "Month": 5, "Hour": 14, "District": 313, "Price": 329.0, "Duration": 36, "Length": 20.4}, {"DayOfWeek": 2, "Month": 5, "Hour": 14, "District": 102, "Price": 951.0, "Duration": 22, "Length": 17.2}, {"DayOfWeek": 2, "Month": 5, "Hour": 14, "District": 963, "Price": 422.0, "Duration": 17, "Length": 6.8}, {"DayOfWeek": 2, "Month": 5, "Hour": 14, "District": 382, "Price": 420.0, "Duration": 16, "Length": 4.5}, {"DayOfWeek": 2, "Month": 5, "Hour": 14, "District": 854, "Price": 864.0, "Duration": 33, "Length": 8.6}, {"DayOfWeek": 2, "Month": 5, "Hour": 14, "District": 427, "Price": 449.0, "Duration": 43, "Length": 24.2}, {"DayOfWeek": 2, "Month": 5, "Hour": 14, "District": 913, "Price": 604.0, "Duration": 35, "Length": 13.0}, {"DayOfWeek": 2, "Month": 5, "Hour": 14, "District": 798, "Price": 309.0, "Duration": 35, "Length": 31.0}, {"DayOfWeek": 2, "Month": 5, "Hour": 14, "District": 871, "Price": 765.0, "Duration": 33, "Length": 12.4}, {"DayOfWeek": 2, "Month": 5, "Hour": 14, "District": 113, "Price": 410.0, "Duration": 16, "Length": 7.0}, {"DayOfWeek": 2, "Month": 5, "Hour": 14, "District": 526, "Price": 329.0, "Duration": 30, "Length": 20.5}, {"DayOfWeek": 2, "Month": 5, "Hour": 14, "District": 891, "Price": 349.0, "Duration": 4, "Length": 1.72}, {"DayOfWeek": 2, "Month": 5, "Hour": 14, "District": 964, "Price": 666.0, "Duration": 36, "Length": 9.3}, {"DayOfWeek": 2, "Month": 5, "Hour": 14, "District": 685, "Price": 956.0, "Duration": 29, "Length": 22.1}, {"DayOfWeek": 2, "Month": 5, "Hour": 14, "District": 442, "Price": 913.0, "Duration": 27, "Length": 21.1}, {"DayOfWeek": 2, "Month": 5, "Hour": 14, "District": 186, "Price": 701.0, "Duration": 25, "Length": 9.6}, {"DayOfWeek": 2, "Month": 5, "Hour": 14, "District": 994, "Price": 908.0, "Duration": 41, "Length": 26.4}, {"DayOfWeek": 2, "Month": 5, "Hour": 14, "District": 688, "Price": 726.0, "Duration": 28, "Length": 11.0}, {"DayOfWeek": 2, "Month": 5, "Hour": 14, "District": 259, "Price": 347.0, "Duration": 15, "Length": 5.5}, {"DayOfWeek": 2, "Month": 5, "Hour": 14, "District": 457, "Price": 436.0, "Duration": 12, "Length": 4.9}, {"DayOfWeek": 2, "Month": 5, "Hour": 14, "District": 894, "Price": 770.0, "Duration": 34, "Length": 12.8}, {"DayOfWeek": 2, "Month": 5, "Hour": 14, "District": 858, "Price": 286.0, "Duration": 5, "Length": 1.86}, {"DayOfWeek": 2, "Month": 5, "Hour": 14, "District": 503, "Price": 955.0, "Duration": 28, "Length": 16.9}, {"DayOfWeek": 2, "Month": 5, "Hour": 14, "District": 979, "Price": 460.0, "Duration": 11, "Length": 5.8}, {"DayOfWeek": 2, "Month": 5, "Hour": 14, "District": 115, "Price": 917.0, "Duration": 38, "Length": 14.0}, {"DayOfWeek": 2, "Month": 5, "Hour": 14, "District": 33, "Price": 743.0, "Duration": 23, "Length": 8.9}, {"DayOfWeek": 2, "Month": 5, "Hour": 14, "District": 325, "Price": 229.0, "Duration": 43, "Length": 26.0}, {"DayOfWeek": 2, "Month": 5, "Hour": 14, "District": 145, "Price": 731.0, "Duration": 32, "Length": 12.9}, {"DayOfWeek": 2, "Month": 5, "Hour": 14, "District": 36, "Price": 501.0, "Duration": 30, "Length": 9.0}, {"DayOfWeek": 2, "Month": 5, "Hour": 14, "District": 477, "Price": 591.0, "Duration": 27, "Length": 10.9}, {"DayOfWeek": 2, "Month": 5, "Hour": 14, "District": 884, "Price": 554.0, "Duration": 16, "Length": 7.4}, {"DayOfWeek": 2, "Month": 5, "Hour": 14, "District": 727, "Price": 636.0, "Duration": 36, "Length": 18.7},{"DayOfWeek": 2, "Month": 5, "Hour": 15, "District": 707, "Price": 562.0, "Duration": 27, "Length": 9.7}, {"DayOfWeek": 2, "Month": 5, "Hour": 15, "District": 385, "Price": 409.0, "Duration": 45, "Length": 23.9}, {"DayOfWeek": 2, "Month": 5, "Hour": 15, "District": 115, "Price": 845.0, "Duration": 36, "Length": 14.0}, {"DayOfWeek": 2, "Month": 5, "Hour": 15, "District": 234, "Price": 349.0, "Duration": 46, "Length": 40.0}, {"DayOfWeek": 2, "Month": 5, "Hour": 15, "District": 352, "Price": 716.0, "Duration": 34, "Length": 37.0}, {"DayOfWeek": 2, "Month": 5, "Hour": 15, "District": 836, "Price": 1019.0, "Duration": 31, "Length": 29.8}, {"DayOfWeek": 2, "Month": 5, "Hour": 15, "District": 901, "Price": 994.0, "Duration": 31, "Length": 23.1}, {"DayOfWeek": 2, "Month": 5, "Hour": 15, "District": 966, "Price": 614.0, "Duration": 12, "Length": 3.3}, {"DayOfWeek": 2, "Month": 5, "Hour": 15, "District": 854, "Price": 629.0, "Duration": 32, "Length": 8.6}, {"DayOfWeek": 2, "Month": 5, "Hour": 15, "District": 526, "Price": 219.0, "Duration": 31, "Length": 20.5}, {"DayOfWeek": 2, "Month": 5, "Hour": 15, "District": 383, "Price": 1112.0, "Duration": 30, "Length": 26.5}, {"DayOfWeek": 2, "Month": 5, "Hour": 15, "District": 220, "Price": 739.0, "Duration": 34, "Length": 10.6}, {"DayOfWeek": 2, "Month": 5, "Hour": 15, "District": 735, "Price": 582.0, "Duration": 19, "Length": 7.6}, {"DayOfWeek": 2, "Month": 5, "Hour": 15, "District": 963, "Price": 358.0, "Duration": 16, "Length": 6.8}, {"DayOfWeek": 2, "Month": 5, "Hour": 15, "District": 701, "Price": 893.0, "Duration": 30, "Length": 25.2}, {"DayOfWeek": 2, "Month": 5, "Hour": 15, "District": 75, "Price": 573.0, "Duration": 27, "Length": 7.6}, {"DayOfWeek": 2, "Month": 5, "Hour": 15, "District": 685, "Price": 808.0, "Duration": 30, "Length": 22.1}, {"DayOfWeek": 2, "Month": 5, "Hour": 15, "District": 40, "Price": 899.0, "Duration": 26, "Length": 5.4}, {"DayOfWeek": 2, "Month": 5, "Hour": 15, "District": 292, "Price": 279.0, "Duration": 43, "Length": 25.7}, {"DayOfWeek": 2, "Month": 5, "Hour": 15, "District": 585, "Price": 369.0, "Duration": 41, "Length": 28.3}, {"DayOfWeek": 2, "Month": 5, "Hour": 15, "District": 195, "Price": 369.0, "Duration": 41, "Length": 28.9}, {"DayOfWeek": 2, "Month": 5, "Hour": 15, "District": 22, "Price": 366.0, "Duration": 17, "Length": 6.6}, {"DayOfWeek": 2, "Month": 5, "Hour": 15, "District": 831, "Price": 667.0, "Duration": 32, "Length": 13.7}, {"DayOfWeek": 2, "Month": 5, "Hour": 15, "District": 454, "Price": 316.0, "Duration": 12, "Length": 5.0}, {"DayOfWeek": 2, "Month": 5, "Hour": 15, "District": 622, "Price": 547.0, "Duration": 18, "Length": 6.1}, {"DayOfWeek": 2, "Month": 5, "Hour": 15, "District": 322, "Price": 483.0, "Duration": 18, "Length": 6.9}, {"DayOfWeek": 2, "Month": 5, "Hour": 15, "District": 351, "Price": 349.0, "Duration": 8, "Length": 4.6}, {"DayOfWeek": 2, "Month": 5, "Hour": 15, "District": 372, "Price": 465.0, "Duration": 17, "Length": 7.2}, {"DayOfWeek": 2, "Month": 5, "Hour": 15, "District": 186, "Price": 594.0, "Duration": 24, "Length": 9.3}, {"DayOfWeek": 2, "Month": 5, "Hour": 15, "District": 711, "Price": 341.0, "Duration": 13, "Length": 5.6}, {"DayOfWeek": 2, "Month": 5, "Hour": 15, "District": 13, "Price": 913.0, "Duration": 45, "Length": 11.1}, {"DayOfWeek": 2, "Month": 5, "Hour": 15, "District": 858, "Price": 230.0, "Duration": 5, "Length": 1.86}, {"DayOfWeek": 2, "Month": 5, "Hour": 15, "District": 374, "Price": 932.0, "Duration": 40, "Length": 5.6}, {"DayOfWeek": 2, "Month": 5, "Hour": 15, "District": 765, "Price": 309.0, "Duration": 46, "Length": 25.8}, {"DayOfWeek": 2, "Month": 5, "Hour": 15, "District": 113, "Price": 324.0, "Duration": 15, "Length": 7.0}, {"DayOfWeek": 2, "Month": 5, "Hour": 15, "District": 864, "Price": 978.0, "Duration": 32, "Length": 26.1}, {"DayOfWeek": 2, "Month": 5, "Hour": 15, "District": 503, "Price": 1223.0, "Duration": 34, "Length": 16.9}, {"DayOfWeek": 2, "Month": 5, "Hour": 15, "District": 715, "Price": 365.0, "Duration": 17, "Length": 7.2}, {"DayOfWeek": 2, "Month": 5, "Hour": 15, "District": 325, "Price": 139.0, "Duration": 42, "Length": 26.0}, {"DayOfWeek": 2, "Month": 5, "Hour": 15, "District": 877, "Price": 250.0, "Duration": 10, "Length": 4.1}, {"DayOfWeek": 2, "Month": 5, "Hour": 15, "District": 525, "Price": 742.0, "Duration": 19, "Length": 10.2}, {"DayOfWeek": 2, "Month": 5, "Hour": 15, "District": 164, "Price": 438.0, "Duration": 20, "Length": 9.1}, {"DayOfWeek": 2, "Month": 5, "Hour": 15, "District": 616, "Price": 610.0, "Duration": 23, "Length": 7.7}, {"DayOfWeek": 2, "Month": 5, "Hour": 15, "District": 508, "Price": 488.0, "Duration": 20, "Length": 7.3}, {"DayOfWeek": 2, "Month": 5, "Hour": 15, "District": 733, "Price": 547.0, "Duration": 20, "Length": 8.6}, {"DayOfWeek": 2, "Month": 5, "Hour": 15, "District": 419, "Price": 770.0, "Duration": 34, "Length": 12.7}, {"DayOfWeek": 2, "Month": 5, "Hour": 15, "District": 450, "Price": 339.0, "Duration": 14, "Length": 4.9}, {"DayOfWeek": 2, "Month": 5, "Hour": 15, "District": 913, "Price": 603.0, "Duration": 33, "Length": 12.6}, {"DayOfWeek": 2, "Month": 5, "Hour": 15, "District": 382, "Price": 751.0, "Duration": 24, "Length": 9.4}, {"DayOfWeek": 2, "Month": 5, "Hour": 15, "District": 131, "Price": 722.0, "Duration": 18, "Length": 22.0}, {"DayOfWeek": 2, "Month": 5, "Hour": 15, "District": 477, "Price": 549.0, "Duration": 29, "Length": 10.9}, {"DayOfWeek": 2, "Month": 5, "Hour": 15, "District": 145, "Price": 829.0, "Duration": 33, "Length": 17.8}, {"DayOfWeek": 2, "Month": 5, "Hour": 15, "District": 46, "Price": 239.0, "Duration": 30, "Length": 26.7}, {"DayOfWeek": 2, "Month": 5, "Hour": 15, "District": 29, "Price": 589.0, "Duration": 23, "Length": 18.1}, {"DayOfWeek": 2, "Month": 5, "Hour": 15, "District": 328, "Price": 600.0, "Duration": 33, "Length": 12.3}, {"DayOfWeek": 2, "Month": 5, "Hour": 15, "District": 355, "Price": 615.0, "Duration": 31, "Length": 9.3}, {"DayOfWeek": 2, "Month": 5, "Hour": 15, "District": 884, "Price": 434.0, "Duration": 15, "Length": 7.4}, {"DayOfWeek": 2, "Month": 5, "Hour": 15, "District": 90, "Price": 1127.0, "Duration": 35, "Length": 27.3}, {"DayOfWeek": 2, "Month": 5, "Hour": 15, "District": 445, "Price": 353.0, "Duration": 18, "Length": 6.9}, {"DayOfWeek": 2, "Month": 5, "Hour": 15, "District": 442, "Price": 825.0, "Duration": 27, "Length": 21.1}, {"DayOfWeek": 2, "Month": 5, "Hour": 15, "District": 427, "Price": 518.0, "Duration": 23, "Length": 13.3}, {"DayOfWeek": 2, "Month": 5, "Hour": 15, "District": 417, "Price": 569.0, "Duration": 23, "Length": 4.3}, {"DayOfWeek": 2, "Month": 5, "Hour": 15, "District": 795, "Price": 401.0, "Duration": 17, "Length": 5.0}, {"DayOfWeek": 2, "Month": 5, "Hour": 15, "District": 964, "Price": 759.0, "Duration": 43, "Length": 7.9}, {"DayOfWeek": 2, "Month": 5, "Hour": 15, "District": 838, "Price": 465.0, "Duration": 22, "Length": 9.6}, {"DayOfWeek": 2, "Month": 5, "Hour": 15, "District": 270, "Price": 369.0, "Duration": 35, "Length": 30.0}, {"DayOfWeek": 2, "Month": 5, "Hour": 15, "District": 634, "Price": 413.0, "Duration": 18, "Length": 5.9}, {"DayOfWeek": 2, "Month": 5, "Hour": 15, "District": 449, "Price": 631.0, "Duration": 32, "Length": 7.8}, {"DayOfWeek": 2, "Month": 5, "Hour": 16, "District": 21, "Price": 711.0, "Duration": 28, "Length": 10.8}, {"DayOfWeek": 2, "Month": 5, "Hour": 16, "District": 762, "Price": 661.0, "Duration": 23, "Length": 9.9}, {"DayOfWeek": 2, "Month": 5, "Hour": 16, "District": 313, "Price": 429.0, "Duration": 48, "Length": 20.1}, {"DayOfWeek": 2, "Month": 5, "Hour": 16, "District": 594, "Price": 705.0, "Duration": 20, "Length": 12.7}, {"DayOfWeek": 2, "Month": 5, "Hour": 16, "District": 102, "Price": 608.0, "Duration": 23, "Length": 17.2}, {"DayOfWeek": 2, "Month": 5, "Hour": 16, "District": 202, "Price": 732.0, "Duration": 37, "Length": 16.0}, {"DayOfWeek": 2, "Month": 5, "Hour": 16, "District": 870, "Price": 830.0, "Duration": 35, "Length": 18.1}, {"DayOfWeek": 2, "Month": 5, "Hour": 16, "District": 693, "Price": 927.0, "Duration": 39, "Length": 16.3}, {"DayOfWeek": 2, "Month": 5, "Hour": 16, "District": 43, "Price": 970.0, "Duration": 36, "Length": 12.3}, {"DayOfWeek": 2, "Month": 5, "Hour": 16, "District": 72, "Price": 740.0, "Duration": 28, "Length": 12.3}, {"DayOfWeek": 2, "Month": 5, "Hour": 16, "District": 103, "Price": 470.0, "Duration": 11, "Length": 2.26}, {"DayOfWeek": 2, "Month": 5, "Hour": 16, "District": 641, "Price": 570.0, "Duration": 18, "Length": 6.5}, {"DayOfWeek": 2, "Month": 5, "Hour": 16, "District": 427, "Price": 239.0, "Duration": 44, "Length": 25.3}, {"DayOfWeek": 2, "Month": 5, "Hour": 16, "District": 618, "Price": 351.0, "Duration": 8, "Length": 3.4}, {"DayOfWeek": 2, "Month": 5, "Hour": 16, "District": 102, "Price": 431.0, "Duration": 20, "Length": 7.3}, {"DayOfWeek": 2, "Month": 5, "Hour": 16, "District": 271, "Price": 547.0, "Duration": 15, "Length": 7.4}, {"DayOfWeek": 2, "Month": 5, "Hour": 16, "District": 145, "Price": 816.0, "Duration": 34, "Length": 12.9}, {"DayOfWeek": 2, "Month": 5, "Hour": 16, "District": 862, "Price": 386.0, "Duration": 16, "Length": 6.8}, {"DayOfWeek": 2, "Month": 5, "Hour": 16, "District": 891, "Price": 299.0, "Duration": 4, "Length": 1.6}, {"DayOfWeek": 2, "Month": 5, "Hour": 16, "District": 362, "Price": 253.0, "Duration": 7, "Length": 2.0}, {"DayOfWeek": 2, "Month": 5, "Hour": 16, "District": 719, "Price": 605.0, "Duration": 23, "Length": 8.5}, {"DayOfWeek": 2, "Month": 5, "Hour": 16, "District": 259, "Price": 373.0, "Duration": 15, "Length": 5.5}, {"DayOfWeek": 2, "Month": 5, "Hour": 16, "District": 688, "Price": 717.0, "Duration": 28, "Length": 10.4}, {"DayOfWeek": 2, "Month": 5, "Hour": 16, "District": 153, "Price": 345.0, "Duration": 13, "Length": 5.5}, {"DayOfWeek": 2, "Month": 5, "Hour": 16, "District": 732, "Price": 545.0, "Duration": 26, "Length": 10.2}, {"DayOfWeek": 2, "Month": 5, "Hour": 16, "District": 798, "Price": 269.0, "Duration": 36, "Length": 31.0}, {"DayOfWeek": 2, "Month": 5, "Hour": 16, "District": 541, "Price": 781.0, "Duration": 22, "Length": 22.1}, {"DayOfWeek": 2, "Month": 5, "Hour": 16, "District": 33, "Price": 697.0, "Duration": 23, "Length": 9.9}, {"DayOfWeek": 2, "Month": 5, "Hour": 16, "District": 353, "Price": 570.0, "Duration": 30, "Length": 9.3}, {"DayOfWeek": 2, "Month": 5, "Hour": 16, "District": 226, "Price": 229.0, "Duration": 6, "Length": 1.95}, {"DayOfWeek": 2, "Month": 5, "Hour": 16, "District": 500, "Price": 470.0, "Duration": 23, "Length": 6.8}, {"DayOfWeek": 2, "Month": 5, "Hour": 16, "District": 565, "Price": 397.0, "Duration": 10, "Length": 3.6}, {"DayOfWeek": 2, "Month": 5, "Hour": 16, "District": 760, "Price": 766.0, "Duration": 32, "Length": 15.9}, {"DayOfWeek": 2, "Month": 5, "Hour": 16, "District": 94, "Price": 503.0, "Duration": 26, "Length": 10.3}, {"DayOfWeek": 2, "Month": 5, "Hour": 16, "District": 598, "Price": 229.0, "Duration": 30, "Length": 20.4}, {"DayOfWeek": 2, "Month": 5, "Hour": 16, "District": 657, "Price": 309.0, "Duration": 33, "Length": 25.8}, {"DayOfWeek": 2, "Month": 5, "Hour": 16, "District": 834, "Price": 763.0, "Duration": 25, "Length": 8.8}, {"DayOfWeek": 2, "Month": 5, "Hour": 16, "District": 174, "Price": 678.0, "Duration": 33, "Length": 16.4}, {"DayOfWeek": 2, "Month": 5, "Hour": 16, "District": 457, "Price": 366.0, "Duration": 12, "Length": 5.0}, {"DayOfWeek": 2, "Month": 5, "Hour": 16, "District": 727, "Price": 893.0, "Duration": 39, "Length": 18.7}, {"DayOfWeek": 2, "Month": 5, "Hour": 16, "District": 894, "Price": 685.0, "Duration": 41, "Length": 12.5}, {"DayOfWeek": 2, "Month": 5, "Hour": 16, "District": 636, "Price": 707.0, "Duration": 42, "Length": 12.7}, {"DayOfWeek": 2, "Month": 5, "Hour": 16, "District": 984, "Price": 754.0, "Duration": 29, "Length": 6.4},{"DayOfWeek": 2, "Month": 5, "Hour": 16, "District": 966, "Price": 649.0, "Duration": 14, "Length": 3.3}, {"DayOfWeek": 2, "Month": 5, "Hour": 16, "District": 174, "Price": 1055.0, "Duration": 44, "Length": 18.0}, {"DayOfWeek": 2, "Month": 5, "Hour": 16, "District": 901, "Price": 1346.0, "Duration": 32, "Length": 23.1}, {"DayOfWeek": 2, "Month": 5, "Hour": 16, "District": 115, "Price": 825.0, "Duration": 52, "Length": 14.0}, {"DayOfWeek": 2, "Month": 5, "Hour": 16, "District": 979, "Price": 407.0, "Duration": 12, "Length": 5.8}, {"DayOfWeek": 2, "Month": 5, "Hour": 16, "District": 36, "Price": 825.0, "Duration": 47, "Length": 7.5}, {"DayOfWeek": 2, "Month": 5, "Hour": 16, "District": 913, "Price": 941.0, "Duration": 35, "Length": 13.0}, {"DayOfWeek": 2, "Month": 5, "Hour": 16, "District": 445, "Price": 394.0, "Duration": 17, "Length": 6.9}, {"DayOfWeek": 2, "Month": 5, "Hour": 16, "District": 834, "Price": 835.0, "Duration": 26, "Length": 8.8}, {"DayOfWeek": 2, "Month": 5, "Hour": 16, "District": 353, "Price": 503.0, "Duration": 31, "Length": 9.3}, {"DayOfWeek": 2, "Month": 5, "Hour": 16, "District": 102, "Price": 436.0, "Duration": 24, "Length": 5.7}, {"DayOfWeek": 2, "Month": 5, "Hour": 16, "District": 693, "Price": 816.0, "Duration": 41, "Length": 16.2}, {"DayOfWeek": 2, "Month": 5, "Hour": 16, "District": 113, "Price": 404.0, "Duration": 15, "Length": 7.0}, {"DayOfWeek": 2, "Month": 5, "Hour": 16, "District": 356, "Price": 494.0, "Duration": 17, "Length": 5.1}, {"DayOfWeek": 2, "Month": 5, "Hour": 16, "District": 328, "Price": 653.0, "Duration": 34, "Length": 10.3}, {"DayOfWeek": 2, "Month": 5, "Hour": 16, "District": 202, "Price": 926.0, "Duration": 40, "Length": 19.2}, {"DayOfWeek": 2, "Month": 5, "Hour": 16, "District": 322, "Price": 448.0, "Duration": 17, "Length": 10.5}, {"DayOfWeek": 2, "Month": 5, "Hour": 16, "District": 760, "Price": 867.0, "Duration": 31, "Length": 15.9}, {"DayOfWeek": 2, "Month": 5, "Hour": 16, "District": 765, "Price": 369.0, "Duration": 48, "Length": 25.2}, {"DayOfWeek": 2, "Month": 5, "Hour": 16, "District": 963, "Price": 395.0, "Duration": 17, "Length": 6.8}, {"DayOfWeek": 2, "Month": 5, "Hour": 16, "District": 145, "Price": 623.0, "Duration": 29, "Length": 12.9}, {"DayOfWeek": 2, "Month": 5, "Hour": 16, "District": 894, "Price": 850.0, "Duration": 36, "Length": 12.8}, {"DayOfWeek": 2, "Month": 5, "Hour": 16, "District": 854, "Price": 774.0, "Duration": 32, "Length": 8.6}, {"DayOfWeek": 2, "Month": 5, "Hour": 16, "District": 836, "Price": 1037.0, "Duration": 32, "Length": 29.8}, {"DayOfWeek": 2, "Month": 5, "Hour": 16, "District": 634, "Price": 354.0, "Duration": 15, "Length": 5.9}, {"DayOfWeek": 2, "Month": 5, "Hour": 16, "District": 292, "Price": 349.0, "Duration": 44, "Length": 25.1}, {"DayOfWeek": 2, "Month": 5, "Hour": 16, "District": 355, "Price": 678.0, "Duration": 27, "Length": 8.8}, {"DayOfWeek": 2, "Month": 5, "Hour": 16, "District": 75, "Price": 897.0, "Duration": 39, "Length": 7.6}, {"DayOfWeek": 2, "Month": 5, "Hour": 16, "District": 449, "Price": 520.0, "Duration": 19, "Length": 6.7}, {"DayOfWeek": 2, "Month": 5, "Hour": 16, "District": 616, "Price": 764.0, "Duration": 24, "Length": 7.7}, {"DayOfWeek": 2, "Month": 5, "Hour": 16, "District": 862, "Price": 534.0, "Duration": 16, "Length": 6.8}, {"DayOfWeek": 2, "Month": 5, "Hour": 16, "District": 798, "Price": 319.0, "Duration": 35, "Length": 31.0}, {"DayOfWeek": 2, "Month": 5, "Hour": 16, "District": 259, "Price": 399.0, "Duration": 20, "Length": 5.5}, {"DayOfWeek": 2, "Month": 5, "Hour": 16, "District": 234, "Price": 369.0, "Duration": 49, "Length": 33.0}, {"DayOfWeek": 2, "Month": 5, "Hour": 16, "District": 417, "Price": 476.0, "Duration": 17, "Length": 4.3}, {"DayOfWeek": 2, "Month": 5, "Hour": 16, "District": 701, "Price": 1572.0, "Duration": 32, "Length": 25.2}, {"DayOfWeek": 2, "Month": 5, "Hour": 16, "District": 565, "Price": 446.0, "Duration": 13, "Length": 3.6}, {"DayOfWeek": 2, "Month": 5, "Hour": 16, "District": 46, "Price": 199.0, "Duration": 30, "Length": 26.7}, {"DayOfWeek": 2, "Month": 5, "Hour": 16, "District": 762, "Price": 656.0, "Duration": 22, "Length": 9.9}, {"DayOfWeek": 2, "Month": 5, "Hour": 16, "District": 594, "Price": 528.0, "Duration": 20, "Length": 12.7}, {"DayOfWeek": 2, "Month": 5, "Hour": 16, "District": 103, "Price": 466.0, "Duration": 11, "Length": 2.26}, {"DayOfWeek": 2, "Month": 5, "Hour": 16, "District": 271, "Price": 495.0, "Duration": 15, "Length": 7.4}, {"DayOfWeek": 2, "Month": 5, "Hour": 16, "District": 22, "Price": 511.0, "Duration": 20, "Length": 8.8}, {"DayOfWeek": 2, "Month": 5, "Hour": 16, "District": 641, "Price": 652.0, "Duration": 20, "Length": 6.5}, {"DayOfWeek": 2, "Month": 5, "Hour": 16, "District": 325, "Price": 199.0, "Duration": 42, "Length": 26.0}, {"DayOfWeek": 2, "Month": 5, "Hour": 16, "District": 270, "Price": 349.0, "Duration": 33, "Length": 30.0}, {"DayOfWeek": 2, "Month": 5, "Hour": 16, "District": 733, "Price": 497.0, "Duration": 20, "Length": 8.6}, {"DayOfWeek": 2, "Month": 5, "Hour": 16, "District": 897, "Price": 462.0, "Duration": 19, "Length": 7.9}, {"DayOfWeek": 2, "Month": 5, "Hour": 16, "District": 984, "Price": 748.0, "Duration": 26, "Length": 6.4}, {"DayOfWeek": 2, "Month": 5, "Hour": 16, "District": 541, "Price": 1488.0, "Duration": 23, "Length": 22.1}, {"DayOfWeek": 2, "Month": 5, "Hour": 16, "District": 450, "Price": 413.0, "Duration": 14, "Length": 5.1}, {"DayOfWeek": 2, "Month": 5, "Hour": 16, "District": 871, "Price": 954.0, "Duration": 41, "Length": 12.0}, {"DayOfWeek": 2, "Month": 5, "Hour": 16, "District": 362, "Price": 378.0, "Duration": 7, "Length": 2.0}, {"DayOfWeek": 2, "Month": 5, "Hour": 16, "District": 40, "Price": 813.0, "Duration": 24, "Length": 5.7}, {"DayOfWeek": 2, "Month": 5, "Hour": 16, "District": 374, "Price": 776.0, "Duration": 41, "Length": 7.3}, {"DayOfWeek": 2, "Month": 5, "Hour": 16, "District": 877, "Price": 283.0, "Duration": 10, "Length": 4.1}, {"DayOfWeek": 2, "Month": 5, "Hour": 16, "District": 33, "Price": 870.0, "Duration": 29, "Length": 8.9}, {"DayOfWeek": 2, "Month": 5, "Hour": 16, "District": 351, "Price": 456.0, "Duration": 9, "Length": 4.6}, {"DayOfWeek": 2, "Month": 5, "Hour": 16, "District": 13, "Price": 974.0, "Duration": 37, "Length": 8.7}, {"DayOfWeek": 2, "Month": 5, "Hour": 16, "District": 382, "Price": 531.0, "Duration": 28, "Length": 9.4}, {"DayOfWeek": 2, "Month": 5, "Hour": 16, "District": 226, "Price": 229.0, "Duration": 6, "Length": 1.95}, {"DayOfWeek": 2, "Month": 5, "Hour": 16, "District": 526, "Price": 199.0, "Duration": 34, "Length": 20.2}, {"DayOfWeek": 2, "Month": 5, "Hour": 16, "District": 131, "Price": 1332.0, "Duration": 19, "Length": 22.0}, {"DayOfWeek": 2, "Month": 5, "Hour": 16, "District": 94, "Price": 574.0, "Duration": 24, "Length": 10.3}, {"DayOfWeek": 2, "Month": 5, "Hour": 16, "District": 503, "Price": 1267.0, "Duration": 30, "Length": 16.9}, {"DayOfWeek": 2, "Month": 5, "Hour": 16, "District": 29, "Price": 279.0, "Duration": 22, "Length": 18.1}, {"DayOfWeek": 2, "Month": 5, "Hour": 16, "District": 685, "Price": 1148.0, "Duration": 36, "Length": 22.1}, {"DayOfWeek": 2, "Month": 5, "Hour": 16, "District": 585, "Price": 389.0, "Duration": 43, "Length": 28.2}, {"DayOfWeek": 2, "Month": 5, "Hour": 16, "District": 636, "Price": 900.0, "Duration": 35, "Length": 12.7}, {"DayOfWeek": 2, "Month": 5, "Hour": 16, "District": 43, "Price": 1110.0, "Duration": 39, "Length": 12.3}, {"DayOfWeek": 2, "Month": 5, "Hour": 16, "District": 864, "Price": 1088.0, "Duration": 33, "Length": 26.1}, {"DayOfWeek": 2, "Month": 5, "Hour": 16, "District": 525, "Price": 681.0, "Duration": 19, "Length": 10.2}, {"DayOfWeek": 2, "Month": 5, "Hour": 16, "District": 831, "Price": 981.0, "Duration": 46, "Length": 13.3}, {"DayOfWeek": 2, "Month": 5, "Hour": 16, "District": 732, "Price": 580.0, "Duration": 22, "Length": 10.2}, {"DayOfWeek": 2, "Month": 5, "Hour": 16, "District": 884, "Price": 439.0, "Duration": 17, "Length": 7.7}, {"DayOfWeek": 2, "Month": 5, "Hour": 16, "District": 727, "Price": 798.0, "Duration": 48, "Length": 20.6}, {"DayOfWeek": 2, "Month": 5, "Hour": 16, "District": 477, "Price": 579.0, "Duration": 27, "Length": 10.9}, {"DayOfWeek": 2, "Month": 5, "Hour": 16, "District": 719, "Price": 758.0, "Duration": 23, "Length": 8.5}, {"DayOfWeek": 2, "Month": 5, "Hour": 16, "District": 72, "Price": 755.0, "Duration": 26, "Length": 12.3}, {"DayOfWeek": 2, "Month": 5, "Hour": 16, "District": 657, "Price": 259.0, "Duration": 31, "Length": 25.8}, {"DayOfWeek": 2, "Month": 5, "Hour": 16, "District": 442, "Price": 1252.0, "Duration": 27, "Length": 23.2}, {"DayOfWeek": 2, "Month": 5, "Hour": 16, "District": 622, "Price": 690.0, "Duration": 26, "Length": 6.1}, {"DayOfWeek": 2, "Month": 5, "Hour": 16, "District": 153, "Price": 345.0, "Duration": 13, "Length": 5.5}, {"DayOfWeek": 2, "Month": 5, "Hour": 16, "District": 274, "Price": 1229.0, "Duration": 18, "Length": 17.6}, {"DayOfWeek": 2, "Month": 5, "Hour": 16, "District": 382, "Price": 573.0, "Duration": 20, "Length": 4.5}, {"DayOfWeek": 2, "Month": 5, "Hour": 16, "District": 964, "Price": 621.0, "Duration": 41, "Length": 8.6}, {"DayOfWeek": 2, "Month": 5, "Hour": 16, "District": 598, "Price": 259.0, "Duration": 32, "Length": 20.4}, {"DayOfWeek": 2, "Month": 5, "Hour": 16, "District": 994, "Price": 870.0, "Duration": 53, "Length": 22.9}, {"DayOfWeek": 2, "Month": 5, "Hour": 16, "District": 804, "Price": 1082.0, "Duration": 33, "Length": 16.9}, {"DayOfWeek": 2, "Month": 5, "Hour": 16, "District": 21, "Price": 754.0, "Duration": 30, "Length": 10.1}, {"DayOfWeek": 2, "Month": 5, "Hour": 16, "District": 352, "Price": 753.0, "Duration": 34, "Length": 37.0}, {"DayOfWeek": 2, "Month": 5, "Hour": 16, "District": 186, "Price": 755.0, "Duration": 27, "Length": 9.3}, {"DayOfWeek": 2, "Month": 5, "Hour": 16, "District": 735, "Price": 619.0, "Duration": 20, "Length": 7.6}, {"DayOfWeek": 2, "Month": 5, "Hour": 16, "District": 711, "Price": 586.0, "Duration": 15, "Length": 5.6}, {"DayOfWeek": 2, "Month": 5, "Hour": 16, "District": 715, "Price": 421.0, "Duration": 18, "Length": 7.2}, {"DayOfWeek": 2, "Month": 5, "Hour": 16, "District": 500, "Price": 780.0, "Duration": 25, "Length": 6.1}, {"DayOfWeek": 2, "Month": 5, "Hour": 16, "District": 164, "Price": 596.0, "Duration": 21, "Length": 11.9}, {"DayOfWeek": 2, "Month": 5, "Hour": 16, "District": 385, "Price": 329.0, "Duration": 1, "Length": 5.0}, {"DayOfWeek": 2, "Month": 5, "Hour": 16, "District": 383, "Price": 1519.0, "Duration": 26, "Length": 26.5}, {"DayOfWeek": 2, "Month": 5, "Hour": 16, "District": 891, "Price": 369.0, "Duration": 4, "Length": 1.6}, {"DayOfWeek": 2, "Month": 5, "Hour": 16, "District": 688, "Price": 787.0, "Duration": 27, "Length": 10.4}, {"DayOfWeek": 2, "Month": 5, "Hour": 16, "District": 372, "Price": 537.0, "Duration": 17, "Length": 7.2}, {"DayOfWeek": 2, "Month": 5, "Hour": 16, "District": 838, "Price": 548.0, "Duration": 25, "Length": 9.6}, {"DayOfWeek": 2, "Month": 5, "Hour": 16, "District": 454, "Price": 332.0, "Duration": 12, "Length": 5.0}, {"DayOfWeek": 2, "Month": 5, "Hour": 16, "District": 313, "Price": 349.0, "Duration": 59, "Length": 31.0}, {"DayOfWeek": 2, "Month": 5, "Hour": 16, "District": 419, "Price": 1031.0, "Duration": 30, "Length": 12.7}, {"DayOfWeek": 2, "Month": 5, "Hour": 16, "District": 707, "Price": 667.0, "Duration": 27, "Length": 10.0}, {"DayOfWeek": 2, "Month": 5, "Hour": 16, "District": 870, "Price": 800.0, "Duration": 35, "Length": 15.2}, {"DayOfWeek": 2, "Month": 5, "Hour": 16, "District": 102, "Price": 1078.0, "Duration": 24, "Length": 17.2}, {"DayOfWeek": 2, "Month": 5, "Hour": 16, "District": 145, "Price": 1116.0, "Duration": 36, "Length": 16.9}, {"DayOfWeek": 2, "Month": 5, "Hour": 16, "District": 457, "Price": 471.0, "Duration": 12, "Length": 4.9}, {"DayOfWeek": 2, "Month": 5, "Hour": 16, "District": 220, "Price": 944.0, "Duration": 31, "Length": 10.3}, {"DayOfWeek": 2, "Month": 5, "Hour": 16, "District": 795, "Price": 376.0, "Duration": 21, "Length": 5.0}, {"DayOfWeek": 2, "Month": 5, "Hour": 16, "District": 195, "Price": 369.0, "Duration": 41, "Length": 28.9},{"DayOfWeek": 2, "Month": 5, "Hour": 17, "District": 525, "Price": 1016.0, "Duration": 28, "Length": 10.2}, {"DayOfWeek": 2, "Month": 5, "Hour": 17, "District": 963, "Price": 337.0, "Duration": 17, "Length": 6.8}, {"DayOfWeek": 2, "Month": 5, "Hour": 17, "District": 427, "Price": 762.0, "Duration": 29, "Length": 13.3}, {"DayOfWeek": 2, "Month": 5, "Hour": 17, "District": 732, "Price": 759.0, "Duration": 31, "Length": 14.4}, {"DayOfWeek": 2, "Month": 5, "Hour": 17, "District": 760, "Price": 913.0, "Duration": 44, "Length": 15.9}, {"DayOfWeek": 2, "Month": 5, "Hour": 17, "District": 445, "Price": 685.0, "Duration": 18, "Length": 6.9}, {"DayOfWeek": 2, "Month": 5, "Hour": 17, "District": 372, "Price": 651.0, "Duration": 22, "Length": 7.2}, {"DayOfWeek": 2, "Month": 5, "Hour": 17, "District": 351, "Price": 488.0, "Duration": 11, "Length": 4.6}, {"DayOfWeek": 2, "Month": 5, "Hour": 17, "District": 871, "Price": 864.0, "Duration": 46, "Length": 9.6}, {"DayOfWeek": 2, "Month": 5, "Hour": 17, "District": 29, "Price": 689.0, "Duration": 27, "Length": 19.6}, {"DayOfWeek": 2, "Month": 5, "Hour": 17, "District": 385, "Price": 369.0, "Duration": 43, "Length": 20.7}, {"DayOfWeek": 2, "Month": 5, "Hour": 17, "District": 616, "Price": 758.0, "Duration": 24, "Length": 7.8}, {"DayOfWeek": 2, "Month": 5, "Hour": 17, "District": 102, "Price": 535.0, "Duration": 26, "Length": 5.7}, {"DayOfWeek": 2, "Month": 5, "Hour": 17, "District": 836, "Price": 1225.0, "Duration": 35, "Length": 29.8}, {"DayOfWeek": 2, "Month": 5, "Hour": 17, "District": 870, "Price": 965.0, "Duration": 44, "Length": 15.2}, {"DayOfWeek": 2, "Month": 5, "Hour": 17, "District": 195, "Price": 329.0, "Duration": 47, "Length": 31.0}, {"DayOfWeek": 2, "Month": 5, "Hour": 17, "District": 733, "Price": 431.0, "Duration": 20, "Length": 8.6}, {"DayOfWeek": 2, "Month": 5, "Hour": 17, "District": 449, "Price": 758.0, "Duration": 32, "Length": 6.7}, {"DayOfWeek": 2, "Month": 5, "Hour": 17, "District": 913, "Price": 880.0, "Duration": 41, "Length": 13.0}, {"DayOfWeek": 2, "Month": 5, "Hour": 17, "District": 500, "Price": 696.0, "Duration": 27, "Length": 6.7}, {"DayOfWeek": 2, "Month": 5, "Hour": 17, "District": 508, "Price": 578.0, "Duration": 21, "Length": 7.1}, {"DayOfWeek": 2, "Month": 5, "Hour": 17, "District": 33, "Price": 919.0, "Duration": 28, "Length": 10.9}, {"DayOfWeek": 2, "Month": 5, "Hour": 17, "District": 765, "Price": 369.0, "Duration": 54, "Length": 22.2}, {"DayOfWeek": 2, "Month": 5, "Hour": 17, "District": 457, "Price": 615.0, "Duration": 12, "Length": 4.9}, {"DayOfWeek": 2, "Month": 5, "Hour": 17, "District": 259, "Price": 402.0, "Duration": 20, "Length": 5.6}, {"DayOfWeek": 2, "Month": 5, "Hour": 17, "District": 442, "Price": 1037.0, "Duration": 31, "Length": 23.2}, {"DayOfWeek": 2, "Month": 5, "Hour": 17, "District": 877, "Price": 335.0, "Duration": 10, "Length": 3.3}, {"DayOfWeek": 2, "Month": 5, "Hour": 17, "District": 21, "Price": 894.0, "Duration": 34, "Length": 10.0}, {"DayOfWeek": 2, "Month": 5, "Hour": 17, "District": 43, "Price": 1156.0, "Duration": 40, "Length": 12.7}, {"DayOfWeek": 2, "Month": 5, "Hour": 17, "District": 838, "Price": 431.0, "Duration": 25, "Length": 9.6}, {"DayOfWeek": 2, "Month": 5, "Hour": 17, "District": 374, "Price": 629.0, "Duration": 29, "Length": 6.3}, {"DayOfWeek": 2, "Month": 5, "Hour": 17, "District": 715, "Price": 472.0, "Duration": 19, "Length": 7.2}, {"DayOfWeek": 2, "Month": 5, "Hour": 17, "District": 585, "Price": 349.0, "Duration": 51, "Length": 28.2}, {"DayOfWeek": 2, "Month": 5, "Hour": 17, "District": 325, "Price": 149.0, "Duration": 48, "Length": 26.1}, {"DayOfWeek": 2, "Month": 5, "Hour": 17, "District": 966, "Price": 759.0, "Duration": 13, "Length": 3.5}, {"DayOfWeek": 2, "Month": 5, "Hour": 17, "District": 270, "Price": 369.0, "Duration": 37, "Length": 29.1}, {"DayOfWeek": 2, "Month": 5, "Hour": 17, "District": 798, "Price": 319.0, "Duration": 37, "Length": 31.0}, {"DayOfWeek": 2, "Month": 5, "Hour": 17, "District": 594, "Price": 671.0, "Duration": 21, "Length": 12.7}, {"DayOfWeek": 2, "Month": 5, "Hour": 17, "District": 454, "Price": 371.0, "Duration": 13, "Length": 5.0}, {"DayOfWeek": 2, "Month": 5, "Hour": 17, "District": 858, "Price": 230.0, "Duration": 5, "Length": 1.86}, {"DayOfWeek": 2, "Month": 5, "Hour": 17, "District": 72, "Price": 861.0, "Duration": 36, "Length": 12.3}, {"DayOfWeek": 2, "Month": 5, "Hour": 17, "District": 383, "Price": 1482.0, "Duration": 28, "Length": 26.5}, {"DayOfWeek": 2, "Month": 5, "Hour": 17, "District": 477, "Price": 937.0, "Duration": 36, "Length": 10.0}, {"DayOfWeek": 2, "Month": 5, "Hour": 17, "District": 174, "Price": 1034.0, "Duration": 47, "Length": 16.3}, {"DayOfWeek": 2, "Month": 5, "Hour": 17, "District": 234, "Price": 409.0, "Duration": 58, "Length": 33.0}, {"DayOfWeek": 2, "Month": 5, "Hour": 17, "District": 427, "Price": 389.0, "Duration": 57, "Length": 25.9}, {"DayOfWeek": 2, "Month": 5, "Hour": 17, "District": 707, "Price": 548.0, "Duration": 30, "Length": 9.7}, {"DayOfWeek": 2, "Month": 5, "Hour": 17, "District": 113, "Price": 333.0, "Duration": 14, "Length": 7.0}, {"DayOfWeek": 2, "Month": 5, "Hour": 17, "District": 994, "Price": 960.0, "Duration": 49, "Length": 17.5}, {"DayOfWeek": 2, "Month": 5, "Hour": 17, "District": 864, "Price": 904.0, "Duration": 38, "Length": 26.1}, {"DayOfWeek": 2, "Month": 5, "Hour": 17, "District": 565, "Price": 562.0, "Duration": 11, "Length": 3.6}, {"DayOfWeek": 2, "Month": 5, "Hour": 17, "District": 979, "Price": 551.0, "Duration": 16, "Length": 5.8}, {"DayOfWeek": 2, "Month": 5, "Hour": 17, "District": 541, "Price": 1263.0, "Duration": 22, "Length": 22.1}, {"DayOfWeek": 2, "Month": 5, "Hour": 17, "District": 622, "Price": 657.0, "Duration": 25, "Length": 5.6}, {"DayOfWeek": 2, "Month": 5, "Hour": 17, "District": 862, "Price": 415.0, "Duration": 16, "Length": 6.8}, {"DayOfWeek": 2, "Month": 5, "Hour": 17, "District": 964, "Price": 1394.0, "Duration": 40, "Length": 8.3}, {"DayOfWeek": 2, "Month": 5, "Hour": 17, "District": 220, "Price": 905.0, "Duration": 36, "Length": 10.3}, {"DayOfWeek": 2, "Month": 5, "Hour": 17, "District": 153, "Price": 435.0, "Duration": 13, "Length": 5.5}, {"DayOfWeek": 2, "Month": 5, "Hour": 17, "District": 131, "Price": 1239.0, "Duration": 18, "Length": 22.0}, {"DayOfWeek": 2, "Month": 5, "Hour": 17, "District": 313, "Price": 329.0, "Duration": 48, "Length": 19.7}, {"DayOfWeek": 2, "Month": 5, "Hour": 17, "District": 103, "Price": 536.0, "Duration": 10, "Length": 2.26}, {"DayOfWeek": 2, "Month": 5, "Hour": 17, "District": 322, "Price": 509.0, "Duration": 17, "Length": 10.5}, {"DayOfWeek": 2, "Month": 5, "Hour": 17, "District": 711, "Price": 558.0, "Duration": 15, "Length": 5.6}, {"DayOfWeek": 2, "Month": 5, "Hour": 17, "District": 641, "Price": 777.0, "Duration": 20, "Length": 6.5}, {"DayOfWeek": 2, "Month": 5, "Hour": 17, "District": 897, "Price": 465.0, "Duration": 23, "Length": 7.9}, {"DayOfWeek": 2, "Month": 5, "Hour": 17, "District": 727, "Price": 1071.0, "Duration": 59, "Length": 18.8}, {"DayOfWeek": 2, "Month": 5, "Hour": 17, "District": 40, "Price": 903.0, "Duration": 25, "Length": 5.2}, {"DayOfWeek": 2, "Month": 5, "Hour": 17, "District": 701, "Price": 1609.0, "Duration": 36, "Length": 25.2}, {"DayOfWeek": 2, "Month": 5, "Hour": 17, "District": 90, "Price": 1450.0, "Duration": 45, "Length": 27.0}, {"DayOfWeek": 2, "Month": 5, "Hour": 17, "District": 352, "Price": 764.0, "Duration": 35, "Length": 37.0}, {"DayOfWeek": 2, "Month": 5, "Hour": 17, "District": 22, "Price": 583.0, "Duration": 24, "Length": 6.6}, {"DayOfWeek": 2, "Month": 5, "Hour": 17, "District": 353, "Price": 717.0, "Duration": 31, "Length": 9.3}, {"DayOfWeek": 2, "Month": 5, "Hour": 17, "District": 657, "Price": 309.0, "Duration": 35, "Length": 25.7}, {"DayOfWeek": 2, "Month": 5, "Hour": 17, "District": 891, "Price": 369.0, "Duration": 4, "Length": 1.6}, {"DayOfWeek": 2, "Month": 5, "Hour": 17, "District": 102, "Price": 1057.0, "Duration": 25, "Length": 18.6}, {"DayOfWeek": 2, "Month": 5, "Hour": 17, "District": 688, "Price": 986.0, "Duration": 32, "Length": 10.4}, {"DayOfWeek": 2, "Month": 5, "Hour": 17, "District": 503, "Price": 1210.0, "Duration": 43, "Length": 17.0}, {"DayOfWeek": 2, "Month": 5, "Hour": 17, "District": 719, "Price": 734.0, "Duration": 25, "Length": 8.5}, {"DayOfWeek": 2, "Month": 5, "Hour": 17, "District": 901, "Price": 1447.0, "Duration": 33, "Length": 23.1}, {"DayOfWeek": 2, "Month": 5, "Hour": 17, "District": 145, "Price": 714.0, "Duration": 37, "Length": 17.8}, {"DayOfWeek": 2, "Month": 5, "Hour": 17, "District": 362, "Price": 418.0, "Duration": 7, "Length": 2.0}, {"DayOfWeek": 2, "Month": 5, "Hour": 17, "District": 419, "Price": 909.0, "Duration": 42, "Length": 12.7}, {"DayOfWeek": 2, "Month": 5, "Hour": 17, "District": 636, "Price": 943.0, "Duration": 40, "Length": 11.3}, {"DayOfWeek": 2, "Month": 5, "Hour": 17, "District": 634, "Price": 633.0, "Duration": 28, "Length": 6.9}, {"DayOfWeek": 2, "Month": 5, "Hour": 17, "District": 36, "Price": 776.0, "Duration": 32, "Length": 7.4}, {"DayOfWeek": 2, "Month": 5, "Hour": 17, "District": 693, "Price": 1118.0, "Duration": 53, "Length": 18.9}, {"DayOfWeek": 2, "Month": 5, "Hour": 17, "District": 328, "Price": 1004.0, "Duration": 41, "Length": 15.0}, {"DayOfWeek": 2, "Month": 5, "Hour": 17, "District": 598, "Price": 219.0, "Duration": 36, "Length": 21.0}, {"DayOfWeek": 2, "Month": 5, "Hour": 17, "District": 417, "Price": 483.0, "Duration": 18, "Length": 4.3}, {"DayOfWeek": 2, "Month": 5, "Hour": 17, "District": 854, "Price": 737.0, "Duration": 37, "Length": 8.8}, {"DayOfWeek": 2, "Month": 5, "Hour": 17, "District": 804, "Price": 1267.0, "Duration": 44, "Length": 17.0}, {"DayOfWeek": 2, "Month": 5, "Hour": 17, "District": 75, "Price": 741.0, "Duration": 33, "Length": 7.2}, {"DayOfWeek": 2, "Month": 5, "Hour": 17, "District": 382, "Price": 748.0, "Duration": 20, "Length": 4.5}, {"DayOfWeek": 2, "Month": 5, "Hour": 17, "District": 356, "Price": 609.0, "Duration": 17, "Length": 5.1}, {"DayOfWeek": 2, "Month": 5, "Hour": 17, "District": 355, "Price": 720.0, "Duration": 30, "Length": 8.8}, {"DayOfWeek": 2, "Month": 5, "Hour": 17, "District": 46, "Price": 319.0, "Duration": 34, "Length": 26.7}, {"DayOfWeek": 2, "Month": 5, "Hour": 17, "District": 292, "Price": 389.0, "Duration": 1, "Length": 22.4}, {"DayOfWeek": 2, "Month": 5, "Hour": 17, "District": 186, "Price": 877.0, "Duration": 33, "Length": 9.7}, {"DayOfWeek": 2, "Month": 5, "Hour": 17, "District": 984, "Price": 838.0, "Duration": 31, "Length": 6.4}, {"DayOfWeek": 2, "Month": 5, "Hour": 17, "District": 450, "Price": 510.0, "Duration": 15, "Length": 4.9}, {"DayOfWeek": 2, "Month": 5, "Hour": 17, "District": 271, "Price": 651.0, "Duration": 17, "Length": 7.4}, {"DayOfWeek": 2, "Month": 5, "Hour": 17, "District": 274, "Price": 1020.0, "Duration": 21, "Length": 17.0}, {"DayOfWeek": 2, "Month": 5, "Hour": 17, "District": 226, "Price": 329.0, "Duration": 6, "Length": 1.95}, {"DayOfWeek": 2, "Month": 5, "Hour": 17, "District": 735, "Price": 580.0, "Duration": 19, "Length": 7.6}, {"DayOfWeek": 2, "Month": 5, "Hour": 17, "District": 94, "Price": 828.0, "Duration": 34, "Length": 10.3}, {"DayOfWeek": 2, "Month": 5, "Hour": 17, "District": 202, "Price": 1176.0, "Duration": 44, "Length": 16.6}, {"DayOfWeek": 2, "Month": 5, "Hour": 17, "District": 382, "Price": 703.0, "Duration": 26, "Length": 9.4}, {"DayOfWeek": 2, "Month": 5, "Hour": 17, "District": 762, "Price": 829.0, "Duration": 25, "Length": 9.9}, {"DayOfWeek": 2, "Month": 5, "Hour": 17, "District": 834, "Price": 962.0, "Duration": 24, "Length": 8.8}, {"DayOfWeek": 2, "Month": 5, "Hour": 17, "District": 526, "Price": 199.0, "Duration": 35, "Length": 20.8}, {"DayOfWeek": 2, "Month": 5, "Hour": 17, "District": 145, "Price": 636.0, "Duration": 28, "Length": 13.3}, {"DayOfWeek": 2, "Month": 5, "Hour": 17, "District": 164, "Price": 644.0, "Duration": 20, "Length": 9.1}, {"DayOfWeek": 2, "Month": 5, "Hour": 17, "District": 115, "Price": 1230.0, "Duration": 50, "Length": 15.6}, {"DayOfWeek": 2, "Month": 5, "Hour": 17, "District": 795, "Price": 491.0, "Duration": 21, "Length": 5.0}, {"DayOfWeek": 2, "Month": 5, "Hour": 17, "District": 884, "Price": 487.0, "Duration": 16, "Length": 7.4},{"DayOfWeek": 2, "Month": 5, "Hour": 18, "District": 836, "Price": 1439.0, "Duration": 33, "Length": 27.1}, {"DayOfWeek": 2, "Month": 5, "Hour": 18, "District": 701, "Price": 1583.0, "Duration": 40, "Length": 25.2}, {"DayOfWeek": 2, "Month": 5, "Hour": 18, "District": 274, "Price": 1313.0, "Duration": 20, "Length": 17.6}, {"DayOfWeek": 2, "Month": 5, "Hour": 18, "District": 102, "Price": 1284.0, "Duration": 27, "Length": 18.6}, {"DayOfWeek": 2, "Month": 5, "Hour": 18, "District": 43, "Price": 1327.0, "Duration": 42, "Length": 12.7}, {"DayOfWeek": 2, "Month": 5, "Hour": 18, "District": 383, "Price": 2050.0, "Duration": 25, "Length": 26.5}, {"DayOfWeek": 2, "Month": 5, "Hour": 18, "District": 29, "Price": 629.0, "Duration": 24, "Length": 18.1}, {"DayOfWeek": 2, "Month": 5, "Hour": 18, "District": 477, "Price": 923.0, "Duration": 38, "Length": 8.9}, {"DayOfWeek": 2, "Month": 5, "Hour": 18, "District": 541, "Price": 1053.0, "Duration": 26, "Length": 22.1}, {"DayOfWeek": 2, "Month": 5, "Hour": 18, "District": 385, "Price": 369.0, "Duration": 47, "Length": 20.7}, {"DayOfWeek": 2, "Month": 5, "Hour": 18, "District": 153, "Price": 463.0, "Duration": 13, "Length": 5.6}, {"DayOfWeek": 2, "Month": 5, "Hour": 18, "District": 427, "Price": 369.0, "Duration": 53, "Length": 25.3}, {"DayOfWeek": 2, "Month": 5, "Hour": 18, "District": 234, "Price": 459.0, "Duration": 56, "Length": 24.0}, {"DayOfWeek": 2, "Month": 5, "Hour": 18, "District": 870, "Price": 1367.0, "Duration": 51, "Length": 15.2}, {"DayOfWeek": 2, "Month": 5, "Hour": 18, "District": 115, "Price": 1056.0, "Duration": 51, "Length": 16.8}, {"DayOfWeek": 2, "Month": 5, "Hour": 18, "District": 891, "Price": 449.0, "Duration": 4, "Length": 1.72}, {"DayOfWeek": 2, "Month": 5, "Hour": 18, "District": 871, "Price": 1145.0, "Duration": 48, "Length": 12.4}, {"DayOfWeek": 2, "Month": 5, "Hour": 18, "District": 897, "Price": 527.0, "Duration": 23, "Length": 5.9}, {"DayOfWeek": 2, "Month": 5, "Hour": 18, "District": 838, "Price": 589.0, "Duration": 29, "Length": 9.6}, {"DayOfWeek": 2, "Month": 5, "Hour": 18, "District": 894, "Price": 974.0, "Duration": 37, "Length": 10.9}, {"DayOfWeek": 2, "Month": 5, "Hour": 18, "District": 616, "Price": 1176.0, "Duration": 24, "Length": 7.7}, {"DayOfWeek": 2, "Month": 5, "Hour": 18, "District": 353, "Price": 757.0, "Duration": 34, "Length": 9.3}, {"DayOfWeek": 2, "Month": 5, "Hour": 18, "District": 798, "Price": 349.0, "Duration": 44, "Length": 31.0}, {"DayOfWeek": 2, "Month": 5, "Hour": 18, "District": 442, "Price": 1148.0, "Duration": 32, "Length": 23.2}, {"DayOfWeek": 2, "Month": 5, "Hour": 18, "District": 732, "Price": 902.0, "Duration": 33, "Length": 14.4}, {"DayOfWeek": 2, "Month": 5, "Hour": 18, "District": 685, "Price": 1145.0, "Duration": 35, "Length": 24.6}, {"DayOfWeek": 2, "Month": 5, "Hour": 18, "District": 90, "Price": 1411.0, "Duration": 38, "Length": 30.0}, {"DayOfWeek": 2, "Month": 5, "Hour": 18, "District": 733, "Price": 522.0, "Duration": 23, "Length": 8.6}, {"DayOfWeek": 2, "Month": 5, "Hour": 18, "District": 445, "Price": 608.0, "Duration": 15, "Length": 6.9}, {"DayOfWeek": 2, "Month": 5, "Hour": 18, "District": 356, "Price": 309.0, "Duration": 17, "Length": 5.1}, {"DayOfWeek": 2, "Month": 5, "Hour": 18, "District": 186, "Price": 1028.0, "Duration": 30, "Length": 9.7}, {"DayOfWeek": 2, "Month": 5, "Hour": 18, "District": 834, "Price": 611.0, "Duration": 25, "Length": 8.8}, {"DayOfWeek": 2, "Month": 5, "Hour": 18, "District": 964, "Price": 914.0, "Duration": 50, "Length": 9.3}, {"DayOfWeek": 2, "Month": 5, "Hour": 18, "District": 598, "Price": 329.0, "Duration": 36, "Length": 20.4}, {"DayOfWeek": 2, "Month": 5, "Hour": 18, "District": 765, "Price": 309.0, "Duration": 52, "Length": 26.5}, {"DayOfWeek": 2, "Month": 5, "Hour": 18, "District": 427, "Price": 934.0, "Duration": 32, "Length": 13.3}, {"DayOfWeek": 2, "Month": 5, "Hour": 18, "District": 382, "Price": 770.0, "Duration": 18, "Length": 4.5}, {"DayOfWeek": 2, "Month": 5, "Hour": 18, "District": 72, "Price": 975.0, "Duration": 31, "Length": 12.3}, {"DayOfWeek": 2, "Month": 5, "Hour": 18, "District": 351, "Price": 472.0, "Duration": 10, "Length": 4.6}, {"DayOfWeek": 2, "Month": 5, "Hour": 18, "District": 565, "Price": 528.0, "Duration": 11, "Length": 3.6}, {"DayOfWeek": 2, "Month": 5, "Hour": 18, "District": 145, "Price": 952.0, "Duration": 40, "Length": 17.0}, {"DayOfWeek": 2, "Month": 5, "Hour": 18, "District": 164, "Price": 481.0, "Duration": 20, "Length": 8.3}, {"DayOfWeek": 2, "Month": 5, "Hour": 18, "District": 21, "Price": 1008.0, "Duration": 30, "Length": 10.0}, {"DayOfWeek": 2, "Month": 5, "Hour": 18, "District": 693, "Price": 985.0, "Duration": 46, "Length": 15.9}, {"DayOfWeek": 2, "Month": 5, "Hour": 18, "District": 103, "Price": 753.0, "Duration": 13, "Length": 2.26}, {"DayOfWeek": 2, "Month": 5, "Hour": 18, "District": 762, "Price": 836.0, "Duration": 25, "Length": 9.9}, {"DayOfWeek": 2, "Month": 5, "Hour": 18, "District": 760, "Price": 1255.0, "Duration": 41, "Length": 15.9}, {"DayOfWeek": 2, "Month": 5, "Hour": 18, "District": 831, "Price": 877.0, "Duration": 44, "Length": 13.7}, {"DayOfWeek": 2, "Month": 5, "Hour": 18, "District": 328, "Price": 903.0, "Duration": 42, "Length": 12.3}, {"DayOfWeek": 2, "Month": 5, "Hour": 18, "District": 862, "Price": 687.0, "Duration": 17, "Length": 6.8}, {"DayOfWeek": 2, "Month": 5, "Hour": 18, "District": 804, "Price": 1188.0, "Duration": 41, "Length": 15.6}, {"DayOfWeek": 2, "Month": 5, "Hour": 18, "District": 618, "Price": 478.0, "Duration": 8, "Length": 3.4}, {"DayOfWeek": 2, "Month": 5, "Hour": 18, "District": 711, "Price": 666.0, "Duration": 14, "Length": 5.6}, {"DayOfWeek": 2, "Month": 5, "Hour": 18, "District": 901, "Price": 1415.0, "Duration": 31, "Length": 24.0}, {"DayOfWeek": 2, "Month": 5, "Hour": 18, "District": 417, "Price": 616.0, "Duration": 17, "Length": 4.3}, {"DayOfWeek": 2, "Month": 5, "Hour": 18, "District": 33, "Price": 959.0, "Duration": 29, "Length": 8.9}, {"DayOfWeek": 2, "Month": 5, "Hour": 18, "District": 526, "Price": 309.0, "Duration": 35, "Length": 20.2}, {"DayOfWeek": 2, "Month": 5, "Hour": 18, "District": 322, "Price": 493.0, "Duration": 19, "Length": 6.9}, {"DayOfWeek": 2, "Month": 5, "Hour": 18, "District": 362, "Price": 385.0, "Duration": 7, "Length": 2.0}, {"DayOfWeek": 2, "Month": 5, "Hour": 18, "District": 355, "Price": 787.0, "Duration": 28, "Length": 9.4}, {"DayOfWeek": 2, "Month": 5, "Hour": 18, "District": 854, "Price": 661.0, "Duration": 32, "Length": 8.8}, {"DayOfWeek": 2, "Month": 5, "Hour": 18, "District": 966, "Price": 1050.0, "Duration": 22, "Length": 3.3}, {"DayOfWeek": 2, "Month": 5, "Hour": 18, "District": 270, "Price": 429.0, "Duration": 42, "Length": 29.1}, {"DayOfWeek": 2, "Month": 5, "Hour": 18, "District": 271, "Price": 728.0, "Duration": 18, "Length": 7.4}, {"DayOfWeek": 2, "Month": 5, "Hour": 18, "District": 259, "Price": 487.0, "Duration": 19, "Length": 5.6}, {"DayOfWeek": 2, "Month": 5, "Hour": 18, "District": 94, "Price": 785.0, "Duration": 29, "Length": 10.3}, {"DayOfWeek": 2, "Month": 5, "Hour": 18, "District": 913, "Price": 1076.0, "Duration": 35, "Length": 12.6}, {"DayOfWeek": 2, "Month": 5, "Hour": 18, "District": 313, "Price": 259.0, "Duration": 50, "Length": 19.7}, {"DayOfWeek": 2, "Month": 5, "Hour": 18, "District": 36, "Price": 848.0, "Duration": 45, "Length": 7.1}, {"DayOfWeek": 2, "Month": 5, "Hour": 18, "District": 450, "Price": 316.0, "Duration": 15, "Length": 5.1}, {"DayOfWeek": 2, "Month": 5, "Hour": 18, "District": 622, "Price": 1109.0, "Duration": 35, "Length": 6.4}, {"DayOfWeek": 2, "Month": 5, "Hour": 18, "District": 195, "Price": 369.0, "Duration": 51, "Length": 28.6}, {"DayOfWeek": 2, "Month": 5, "Hour": 18, "District": 688, "Price": 1030.0, "Duration": 33, "Length": 10.8}, {"DayOfWeek": 2, "Month": 5, "Hour": 18, "District": 795, "Price": 418.0, "Duration": 22, "Length": 5.0}, {"DayOfWeek": 2, "Month": 5, "Hour": 18, "District": 202, "Price": 1458.0, "Duration": 48, "Length": 19.2}, {"DayOfWeek": 2, "Month": 5, "Hour": 18, "District": 657, "Price": 369.0, "Duration": 38, "Length": 25.7}, {"DayOfWeek": 2, "Month": 5, "Hour": 18, "District": 984, "Price": 810.0, "Duration": 26, "Length": 6.4}, {"DayOfWeek": 2, "Month": 5, "Hour": 18, "District": 40, "Price": 1425.0, "Duration": 39, "Length": 5.2}, {"DayOfWeek": 2, "Month": 5, "Hour": 18, "District": 503, "Price": 1416.0, "Duration": 42, "Length": 16.9}, {"DayOfWeek": 2, "Month": 5, "Hour": 18, "District": 735, "Price": 599.0, "Duration": 18, "Length": 7.1}, {"DayOfWeek": 2, "Month": 5, "Hour": 18, "District": 372, "Price": 568.0, "Duration": 23, "Length": 7.4}, {"DayOfWeek": 2, "Month": 5, "Hour": 18, "District": 715, "Price": 428.0, "Duration": 20, "Length": 7.2}, {"DayOfWeek": 2, "Month": 5, "Hour": 18, "District": 858, "Price": 299.0, "Duration": 5, "Length": 1.86}, {"DayOfWeek": 2, "Month": 5, "Hour": 18, "District": 46, "Price": 319.0, "Duration": 38, "Length": 26.6}, {"DayOfWeek": 2, "Month": 5, "Hour": 18, "District": 449, "Price": 759.0, "Duration": 23, "Length": 6.7}, {"DayOfWeek": 2, "Month": 5, "Hour": 18, "District": 727, "Price": 1255.0, "Duration": 1, "Length": 4.0}, {"DayOfWeek": 2, "Month": 5, "Hour": 18, "District": 994, "Price": 826.0, "Duration": 47, "Length": 18.5}, {"DayOfWeek": 2, "Month": 5, "Hour": 18, "District": 174, "Price": 1199.0, "Duration": 43, "Length": 16.9}, {"DayOfWeek": 2, "Month": 5, "Hour": 18, "District": 457, "Price": 679.0, "Duration": 14, "Length": 5.1}, {"DayOfWeek": 2, "Month": 5, "Hour": 18, "District": 525, "Price": 967.0, "Duration": 31, "Length": 10.2}, {"DayOfWeek": 2, "Month": 5, "Hour": 18, "District": 719, "Price": 577.0, "Duration": 25, "Length": 8.5}, {"DayOfWeek": 2, "Month": 5, "Hour": 18, "District": 585, "Price": 459.0, "Duration": 49, "Length": 28.1}, {"DayOfWeek": 2, "Month": 5, "Hour": 18, "District": 594, "Price": 690.0, "Duration": 21, "Length": 12.7}, {"DayOfWeek": 2, "Month": 5, "Hour": 18, "District": 352, "Price": 756.0, "Duration": 41, "Length": 35.0}, {"DayOfWeek": 2, "Month": 5, "Hour": 18, "District": 963, "Price": 464.0, "Duration": 23, "Length": 6.8}, {"DayOfWeek": 2, "Month": 5, "Hour": 18, "District": 374, "Price": 864.0, "Duration": 40, "Length": 5.6}, {"DayOfWeek": 2, "Month": 5, "Hour": 18, "District": 113, "Price": 332.0, "Duration": 14, "Length": 7.0}, {"DayOfWeek": 2, "Month": 5, "Hour": 18, "District": 382, "Price": 725.0, "Duration": 26, "Length": 9.4}, {"DayOfWeek": 2, "Month": 5, "Hour": 18, "District": 419, "Price": 1092.0, "Duration": 37, "Length": 12.7}, {"DayOfWeek": 2, "Month": 5, "Hour": 18, "District": 13, "Price": 1178.0, "Duration": 52, "Length": 11.2}, {"DayOfWeek": 2, "Month": 5, "Hour": 18, "District": 636, "Price": 950.0, "Duration": 35, "Length": 11.3}, {"DayOfWeek": 2, "Month": 5, "Hour": 18, "District": 884, "Price": 485.0, "Duration": 17, "Length": 7.4}, {"DayOfWeek": 2, "Month": 5, "Hour": 18, "District": 500, "Price": 1041.0, "Duration": 40, "Length": 6.9}, {"DayOfWeek": 2, "Month": 5, "Hour": 18, "District": 707, "Price": 596.0, "Duration": 32, "Length": 9.7}, {"DayOfWeek": 2, "Month": 5, "Hour": 18, "District": 226, "Price": 201.0, "Duration": 6, "Length": 1.95}, {"DayOfWeek": 2, "Month": 5, "Hour": 18, "District": 634, "Price": 544.0, "Duration": 25, "Length": 5.9}, {"DayOfWeek": 2, "Month": 5, "Hour": 18, "District": 864, "Price": 1128.0, "Duration": 31, "Length": 26.1}, {"DayOfWeek": 2, "Month": 5, "Hour": 18, "District": 454, "Price": 390.0, "Duration": 14, "Length": 5.0}, {"DayOfWeek": 2, "Month": 5, "Hour": 18, "District": 102, "Price": 497.0, "Duration": 24, "Length": 7.3}, {"DayOfWeek": 2, "Month": 5, "Hour": 18, "District": 22, "Price": 551.0, "Duration": 23, "Length": 6.6}, {"DayOfWeek": 2, "Month": 5, "Hour": 18, "District": 220, "Price": 1008.0, "Duration": 31, "Length": 10.0}, {"DayOfWeek": 2, "Month": 5, "Hour": 18, "District": 325, "Price": 119.0, "Duration": 41, "Length": 26.1}, {"DayOfWeek": 2, "Month": 5, "Hour": 18, "District": 641, "Price": 908.0, "Duration": 19, "Length": 6.5}, {"DayOfWeek": 2, "Month": 5, "Hour": 18, "District": 131, "Price": 1674.0, "Duration": 18, "Length": 22.0}]